Workbook

Sheet Dashboard
A1: Tổng hợp đăng ký bán hàng nội bộ
A2: Số liệu tự tính từ sheet Registrations và Slots. Ô nền vàng ở sheet Config là ô cần điền.
A4: 1. Theo kho
A5: Kho | B5: Tổng slot | C5: Đã đăng ký | D5: Còn trống | E5: Tỷ lệ đã đăng ký
A6: AYA | B6: =COUNTIF(Slots!$A$2:$A$91,$A6) -> 44 | C6: =COUNTIFS(Slots!$A$2:$A$91,$A6,Slots!$E$2:$E$91,"<>Còn trống") -> 0 | D6: =B6-C6 -> 44 | E6: =IF(B6=0,0,C6/B6) -> 0
A7: AYB | B7: =COUNTIF(Slots!$A$2:$A$91,$A7) -> 1 | C7: =COUNTIFS(Slots!$A$2:$A$91,$A7,Slots!$E$2:$E$91,"<>Còn trống") -> 0 | D7: =B7-C7 -> 1 | E7: =IF(B7=0,0,C7/B7) -> 0
A8: AYC | B8: =COUNTIF(Slots!$A$2:$A$91,$A8) -> 45 | C8: =COUNTIFS(Slots!$A$2:$A$91,$A8,Slots!$E$2:$E$91,"<>Còn trống") -> 0 | D8: =B8-C8 -> 45 | E8: =IF(B8=0,0,C8/B8) -> 0
A9: Tổng | B9: =SUM(B6:B8) -> 90 | C9: =SUM(C6:C8) -> 0 | D9: =SUM(D6:D8) -> 90 | E9: =IF(B9=0,0,C9/B9) -> 0
A11: 2. Theo trạng thái đơn
A12: Trạng thái | B12: Số đơn
A13: Chờ nộp tiền | B13: =COUNTIF(Registrations!$L$2:$L1000,$A13) -> 0
A14: Đã khai nộp - chờ đối soát | B14: =COUNTIF(Registrations!$L$2:$L1000,$A14) -> 0
A15: Đã xác nhận | B15: =COUNTIF(Registrations!$L$2:$L1000,$A15) -> 0
A16: Từ chối | B16: =COUNTIF(Registrations!$L$2:$L1000,$A16) -> 0
A17: Hủy | B17: =COUNTIF(Registrations!$L$2:$L1000,$A17) -> 0
A18: Chưa có trạng thái | B18: =COUNTIFS(Registrations!$D$2:$D1000,"<>",Registrations!$L$2:$L1000,"") -> 0
A19: Tổng số đơn | B19: =SUM(B13:B18) -> 0
A21: 3. Kiểm soát (Jeong-Do)
A22: Chỉ tiêu | B22: Kết quả | C22: Cần làm khi khác 0
A23: Tổng lượt đăng ký | B23: =COUNTA(Registrations!$D$2:$D1000) -> 0
A24: Số mã NV khác nhau | B24: =IFERROR(__xludf.DUMMYFUNCTION("COUNTUNIQUE(Registrations!$D$2:$D1000)"),0.0) -> 0
A25: Lượt đăng ký vượt hạn mức 1 SP/NV | B25: =B23-B24 -> 0 | C25: Lọc cột Mã NV (tô đỏ) để xử lý đơn thừa
A26: Slot bị đăng ký trùng | B26: =COUNTIF(Slots!$E$2:$E$91,"Trùng đăng ký") -> 0 | C26: Xét theo Timestamp, giữ người đến trước
A27: Đăng ký sai kho so với slot | B27: =COUNTIF(Slots!$I$2:$I$91,"Sai kho") -> 0 | C27: Liên hệ NV xác nhận lại kho
A28: Slot không có trong danh sách | B28: =SUMPRODUCT((Registrations!$H$2:$H1000<>"")*(COUNTIF(Slots!$C$2:$C$91,Registrations!$H$2:$H1000)=0)) -> 0 | C28: Kiểm tra mã slot NV nhập
A29: Chưa xác nhận cam kết Jeong-Do | B29: =COUNTIFS(Registrations!$D$2:$D1000,"<>",Registrations!$K$2:$K1000,"<>Đồng ý") -> 0 | C29: Yêu cầu NV xác nhận trước khi giao hàng
A30: Nộp hộ (người nộp khác người đăng ký) | B30: =SUMPRODUCT((Registrations!$N$2:$N1000<>"")*(Registrations!$N$2:$N1000<>Registrations!$D$2:$D1000)) -> 0 | C30: Đối chiếu sao kê theo tên người nộp

Sheet PM xử lý
A1: PM xử lý: danh sách đơn cần đối soát
A2: ="Chờ đối soát: "&COUNTIF(Registrations!$L$2:$L1000,"Đã khai nộp - chờ đối soát")&" | Chờ nộp tiền: "&COUNTIF(Registrations!$L$2:$L1000,"Chờ nộp tiền")&" | Đã xác nhận: "&COUNTIF(Registrations!$L$2:$L1000,"Đã xác nhận")&" | Nộp hộ: "&SUMPRODUCT((Registrations!$M$2:$M1000<>"")*(UPPER(Registrations!$N$2:$N1000)<>UPPER(Registrations!$D$2:$D1000))) -> Chờ đối soát: 0 | Chờ nộp tiền: 0 | Đã xác nhận: 0 | Nộp hộ: 0
A3: Sheet này tự cập nhật và chỉ để xem. Đơn chờ đối soát xếp trên cùng, rồi theo thứ tự thời gian. Muốn đổi trạng thái: bấm "Sửa dòng" ở cột A để nhảy tới đúng dòng trong Registrations, chọn trạng thái ở cột L.
A5: Sửa | B5: Trạng thái | C5: Thời gian đăng ký | D5: Mã NV | E5: Họ tên | F5: Bộ phận | G5: Kho | H5: Slot | I5: Model | J5: NV nộp tiền | K5: Mã NV nộp | L5: Nộp hộ? | M5: Số tiền | N5: Ngân hàng & Mã GD | O5: Giờ nộp | P5: Biên lai | Q5: Ghi chú
A6: =IFERROR(__xludf.DUMMYFUNCTION("IFERROR(ARRAYFORMULA(SORT(FILTER({HYPERLINK(""#gid=1&range=L""&ROW(Registrations!$A$2:$A1000),""Sửa dòng ""&ROW(Registrations!$A$2:$A1000)),Registrations!$L$2:$L1000,Registrations!$A$2:$A1000,Registrations!$D$2:$D1000,Registrations!$E$2:$E1000,Registratio"&"ns!$C$2:$C1000,Registrations!$F$2:$F1000,Registrations!$H$2:$H1000,Registrations!$G$2:$G1000,Registrations!$M$2:$M1000,Registrations!$N$2:$N1000,IF(Registrations!$M$2:$M1000="""","""",IF(UPPER(Registrations!$N$2:$N1000)=UPPER(Registrations!$D$2:$D1000),"""&""",""Nộp hộ"")),Registrations!$O$2:$O1000,Registrations!$P$2:$P1000,Registrations!$Q$2:$Q1000,IF(Registrations!$R$2:$R1000="""","""",HYPERLINK(Registrations!$R$2:$R1000,""Xem biên lai"")),Registrations!$U$2:$U1000},Registrations!$D$2:$D1000<>""""),FILTER("&"IFERROR(MATCH(Registrations!$L$2:$L1000,{""Đã khai nộp - chờ đối soát"",""Chờ nộp tiền"",""Đã xác nhận"",""Từ chối"",""Hủy""},0),9),Registrations!$D$2:$D1000<>""""),TRUE,FILTER(Registrations!$A$2:$A1000,Registrations!$D$2:$D1000<>""""),TRUE)),""Chưa có đơ"&"n"")"),"Chưa có đơn") -> Chưa có đơn

Sheet Registrations
A1: Timestamp | B1: Mã Đợt | C1: Bộ Phận | D1: Mã NV Đăng Ký | E1: Họ Tên NV Đăng Ký | F1: Kho | G1: Mã Model | H1: Slot ID | I1: Số Điện Thoại | J1: Địa Chỉ Giao Hàng | K1: Cam Kết Jeong-Do | L1: Trạng Thái | M1: Họ Tên NV Nộp Tiền | N1: Mã NV Nộp Tiền | O1: Số Tiền Đã Chuyển Khoản | P1: Ngân Hàng & Mã GD | Q1: Thời Gian Nộp Tiền | R1: Link Biên Lai | S1: PM Xác Nhận Bởi | T1: Ngày PM Xác Nhận | U1: Ghi Chú | V1: User Agent | W1: Mã yêu cầu (hệ thống)

Sheet Slots
A1: WH (Kho) | B1: No | C1: Slot ID | D1: Model | E1: Trạng Thái Slot | F1: Số Lượt Đăng Ký | G1: Mã NV Đăng Ký | H1: Họ Tên NV Đăng Ký | I1: Khớp Kho | J1: Loại (Grade) | K1: Giá bán (VNĐ)
A2: AYC | B2: 1 | C2: #001 | D2: 27LX6TDGA.ATV | E2: =IF(F2=0,"Còn trống",IF(F2=1,"Đã đăng ký","Trùng đăng ký")) -> Còn trống | F2: =COUNTIFS(Registrations!$H$2:$H100,$C2,Registrations!$L$2:$L100,"<>Hủy",Registrations!$L$2:$L100,"<>Từ chối") -> 0 | G2: =IFERROR(__xludf.DUMMYFUNCTION("IFERROR(INDEX(FILTER(Registrations!$D$2:$D100,Registrations!$H$2:$H100=$C2,Registrations!$L$2:$L100<>""Hủy"",Registrations!$L$2:$L100<>""Từ chối""),1),"""")"),"") | H2: =IFERROR(__xludf.DUMMYFUNCTION("IFERROR(INDEX(FILTER(Registrations!$E$2:$E100,Registrations!$H$2:$H100=$C2,Registrations!$L$2:$L100<>""Hủy"",Registrations!$L$2:$L100<>""Từ chối""),1),"""")"),"") | I2: =IFERROR(__xludf.DUMMYFUNCTION("IF(F2=0,"""",IF(IFERROR(INDEX(FILTER(Registrations!$F$2:$F100,Registrations!$H$2:$H100=$C2,Registrations!$L$2:$L100<>""Hủy"",Registrations!$L$2:$L100<>""Từ chối""),1),"""")=$A2,""Khớp"",""Sai kho""))"),"") | J2: A | K2: 5085000
A3: AYC | B3: 2 | C3: #002 | D3: 43UA8450PSA.ATV | E3: =IF(F3=0,"Còn trống",IF(F3=1,"Đã đăng ký","Trùng đăng ký")) -> Còn trống | F3: =COUNTIFS(Registrations!$H$2:$H100,$C3,Registrations!$L$2:$L100,"<>Hủy",Registrations!$L$2:$L100,"<>Từ chối") -> 0 | G3: =IFERROR(__xludf.DUMMYFUNCTION("IFERROR(INDEX(FILTER(Registrations!$D$2:$D100,Registrations!$H$2:$H100=$C3,Registrations!$L$2:$L100<>""Hủy"",Registrations!$L$2:$L100<>""Từ chối""),1),"""")"),"") | H3: =IFERROR(__xludf.DUMMYFUNCTION("IFERROR(INDEX(FILTER(Registrations!$E$2:$E100,Registrations!$H$2:$H100=$C3,Registrations!$L$2:$L100<>""Hủy"",Registrations!$L$2:$L100<>""Từ chối""),1),"""")"),"") | I3: =IFERROR(__xludf.DUMMYFUNCTION("IF(F3=0,"""",IF(IFERROR(INDEX(FILTER(Registrations!$F$2:$F100,Registrations!$H$2:$H100=$C3,Registrations!$L$2:$L100<>""Hủy"",Registrations!$L$2:$L100<>""Từ chối""),1),"""")=$A3,""Khớp"",""Sai kho""))"),"") | J3: B | K3: 2672500
A4: AYC | B4: 3 | C4: #003 | D4: 43UQ7050PSA.ATVQ | E4: =IF(F4=0,"Còn trống",IF(F4=1,"Đã đăng ký","Trùng đăng ký")) -> Còn trống | F4: =COUNTIFS(Registrations!$H$2:$H100,$C4,Registrations!$L$2:$L100,"<>Hủy",Registrations!$L$2:$L100,"<>Từ chối") -> 0 | G4: =IFERROR(__xludf.DUMMYFUNCTION("IFERROR(INDEX(FILTER(Registrations!$D$2:$D100,Registrations!$H$2:$H100=$C4,Registrations!$L$2:$L100<>""Hủy"",Registrations!$L$2:$L100<>""Từ chối""),1),"""")"),"") | H4: =IFERROR(__xludf.DUMMYFUNCTION("IFERROR(INDEX(FILTER(Registrations!$E$2:$E100,Registrations!$H$2:$H100=$C4,Registrations!$L$2:$L100<>""Hủy"",Registrations!$L$2:$L100<>""Từ chối""),1),"""")"),"") | I4: =IFERROR(__xludf.DUMMYFUNCTION("IF(F4=0,"""",IF(IFERROR(INDEX(FILTER(Registrations!$F$2:$F100,Registrations!$H$2:$H100=$C4,Registrations!$L$2:$L100<>""Hủy"",Registrations!$L$2:$L100<>""Từ chối""),1),"""")=$A4,""Khớp"",""Sai kho""))"),"") | J4: B | K4: 2672500
A5: AYC | B5: 4 | C5: #004 | D5: 55QNED86ASA.ATV | E5: =IF(F5=0,"Còn trống",IF(F5=1,"Đã đăng ký","Trùng đăng ký")) -> Còn trống | F5: =COUNTIFS(Registrations!$H$2:$H100,$C5,Registrations!$L$2:$L100,"<>Hủy",Registrations!$L$2:$L100,"<>Từ chối") -> 0 | G5: =IFERROR(__xludf.DUMMYFUNCTION("IFERROR(INDEX(FILTER(Registrations!$D$2:$D100,Registrations!$H$2:$H100=$C5,Registrations!$L$2:$L100<>""Hủy"",Registrations!$L$2:$L100<>""Từ chối""),1),"""")"),"") | H5: =IFERROR(__xludf.DUMMYFUNCTION("IFERROR(INDEX(FILTER(Registrations!$E$2:$E100,Registrations!$H$2:$H100=$C5,Registrations!$L$2:$L100<>""Hủy"",Registrations!$L$2:$L100<>""Từ chối""),1),"""")"),"") | I5: =IFERROR(__xludf.DUMMYFUNCTION("IF(F5=0,"""",IF(IFERROR(INDEX(FILTER(Registrations!$F$2:$F100,Registrations!$H$2:$H100=$C5,Registrations!$L$2:$L100<>""Hủy"",Registrations!$L$2:$L100<>""Từ chối""),1),"""")=$A5,""Khớp"",""Sai kho""))"),"") | J5: B | K5: 5850000
A6: AYC | B6: 5 | C6: #005 | D6: 55QNED86BSA.ATV | E6: =IF(F6=0,"Còn trống",IF(F6=1,"Đã đăng ký","Trùng đăng ký")) -> Còn trống | F6: =COUNTIFS(Registrations!$H$2:$H100,$C6,Registrations!$L$2:$L100,"<>Hủy",Registrations!$L$2:$L100,"<>Từ chối") -> 0 | G6: =IFERROR(__xludf.DUMMYFUNCTION("IFERROR(INDEX(FILTER(Registrations!$D$2:$D100,Registrations!$H$2:$H100=$C6,Registrations!$L$2:$L100<>""Hủy"",Registrations!$L$2:$L100<>""Từ chối""),1),"""")"),"") | H6: =IFERROR(__xludf.DUMMYFUNCTION("IFERROR(INDEX(FILTER(Registrations!$E$2:$E100,Registrations!$H$2:$H100=$C6,Registrations!$L$2:$L100<>""Hủy"",Registrations!$L$2:$L100<>""Từ chối""),1),"""")"),"") | I6: =IFERROR(__xludf.DUMMYFUNCTION("IF(F6=0,"""",IF(IFERROR(INDEX(FILTER(Registrations!$F$2:$F100,Registrations!$H$2:$H100=$C6,Registrations!$L$2:$L100<>""Hủy"",Registrations!$L$2:$L100<>""Từ chối""),1),"""")=$A6,""Khớp"",""Sai kho""))"),"") | J6: B | K6: 5975000
A7: AYC | B7: 6 | C7: #006 | D7: 55UA8450PSA.ATV | E7: =IF(F7=0,"Còn trống",IF(F7=1,"Đã đăng ký","Trùng đăng ký")) -> Còn trống | F7: =COUNTIFS(Registrations!$H$2:$H100,$C7,Registrations!$L$2:$L100,"<>Hủy",Registrations!$L$2:$L100,"<>Từ chối") -> 0 | G7: =IFERROR(__xludf.DUMMYFUNCTION("IFERROR(INDEX(FILTER(Registrations!$D$2:$D100,Registrations!$H$2:$H100=$C7,Registrations!$L$2:$L100<>""Hủy"",Registrations!$L$2:$L100<>""Từ chối""),1),"""")"),"") | H7: =IFERROR(__xludf.DUMMYFUNCTION("IFERROR(INDEX(FILTER(Registrations!$E$2:$E100,Registrations!$H$2:$H100=$C7,Registrations!$L$2:$L100<>""Hủy"",Registrations!$L$2:$L100<>""Từ chối""),1),"""")"),"") | I7: =IFERROR(__xludf.DUMMYFUNCTION("IF(F7=0,"""",IF(IFERROR(INDEX(FILTER(Registrations!$F$2:$F100,Registrations!$H$2:$H100=$C7,Registrations!$L$2:$L100<>""Hủy"",Registrations!$L$2:$L100<>""Từ chối""),1),"""")=$A7,""Khớp"",""Sai kho""))"),"") | J7: B | K7: 3897500
A8: AYC | B8: 7 | C8: #007 | D8: 65QNED80BSA.ATV | E8: =IF(F8=0,"Còn trống",IF(F8=1,"Đã đăng ký","Trùng đăng ký")) -> Còn trống | F8: =COUNTIFS(Registrations!$H$2:$H100,$C8,Registrations!$L$2:$L100,"<>Hủy",Registrations!$L$2:$L100,"<>Từ chối") -> 0 | G8: =IFERROR(__xludf.DUMMYFUNCTION("IFERROR(INDEX(FILTER(Registrations!$D$2:$D100,Registrations!$H$2:$H100=$C8,Registrations!$L$2:$L100<>""Hủy"",Registrations!$L$2:$L100<>""Từ chối""),1),"""")"),"") | H8: =IFERROR(__xludf.DUMMYFUNCTION("IFERROR(INDEX(FILTER(Registrations!$E$2:$E100,Registrations!$H$2:$H100=$C8,Registrations!$L$2:$L100<>""Hủy"",Registrations!$L$2:$L100<>""Từ chối""),1),"""")"),"") | I8: =IFERROR(__xludf.DUMMYFUNCTION("IF(F8=0,"""",IF(IFERROR(INDEX(FILTER(Registrations!$F$2:$F100,Registrations!$H$2:$H100=$C8,Registrations!$L$2:$L100<>""Hủy"",Registrations!$L$2:$L100<>""Từ chối""),1),"""")=$A8,""Khớp"",""Sai kho""))"),"") | J8: B | K8: 6350000
A9: AYC | B9: 8 | C9: #008 | D9: 65QNED86ASA.ATV | E9: =IF(F9=0,"Còn trống",IF(F9=1,"Đã đăng ký","Trùng đăng ký")) -> Còn trống | F9: =COUNTIFS(Registrations!$H$2:$H100,$C9,Registrations!$L$2:$L100,"<>Hủy",Registrations!$L$2:$L100,"<>Từ chối") -> 0 | G9: =IFERROR(__xludf.DUMMYFUNCTION("IFERROR(INDEX(FILTER(Registrations!$D$2:$D100,Registrations!$H$2:$H100=$C9,Registrations!$L$2:$L100<>""Hủy"",Registrations!$L$2:$L100<>""Từ chối""),1),"""")"),"") | H9: =IFERROR(__xludf.DUMMYFUNCTION("IFERROR(INDEX(FILTER(Registrations!$E$2:$E100,Registrations!$H$2:$H100=$C9,Registrations!$L$2:$L100<>""Hủy"",Registrations!$L$2:$L100<>""Từ chối""),1),"""")"),"") | I9: =IFERROR(__xludf.DUMMYFUNCTION("IF(F9=0,"""",IF(IFERROR(INDEX(FILTER(Registrations!$F$2:$F100,Registrations!$H$2:$H100=$C9,Registrations!$L$2:$L100<>""Hủy"",Registrations!$L$2:$L100<>""Từ chối""),1),"""")=$A9,""Khớp"",""Sai kho""))"),"") | J9: B | K9: 7322500
A10: AYC | B10: 9 | C10: #009 | D10: 65QNED86BSA.ATV | E10: =IF(F10=0,"Còn trống",IF(F10=1,"Đã đăng ký","Trùng đăng ký")) -> Còn trống | F10: =COUNTIFS(Registrations!$H$2:$H100,$C10,Registrations!$L$2:$L100,"<>Hủy",Registrations!$L$2:$L100,"<>Từ chối") -> 0 | G10: =IFERROR(__xludf.DUMMYFUNCTION("IFERROR(INDEX(FILTER(Registrations!$D$2:$D100,Registrations!$H$2:$H100=$C10,Registrations!$L$2:$L100<>""Hủy"",Registrations!$L$2:$L100<>""Từ chối""),1),"""")"),"") | H10: =IFERROR(__xludf.DUMMYFUNCTION("IFERROR(INDEX(FILTER(Registrations!$E$2:$E100,Registrations!$H$2:$H100=$C10,Registrations!$L$2:$L100<>""Hủy"",Registrations!$L$2:$L100<>""Từ chối""),1),"""")"),"") | I10: =IFERROR(__xludf.DUMMYFUNCTION("IF(F10=0,"""",IF(IFERROR(INDEX(FILTER(Registrations!$F$2:$F100,Registrations!$H$2:$H100=$C10,Registrations!$L$2:$L100<>""Hủy"",Registrations!$L$2:$L100<>""Từ chối""),1),"""")=$A10,""Khớp"",""Sai kho""))"),"") | J10: B | K10: 7475000
A11: AYC | B11: 10 | C11: #010 | D11: 75QNED82ASA.AGADLHX | E11: =IF(F11=0,"Còn trống",IF(F11=1,"Đã đăng ký","Trùng đăng ký")) -> Còn trống | F11: =COUNTIFS(Registrations!$H$2:$H100,$C11,Registrations!$L$2:$L100,"<>Hủy",Registrations!$L$2:$L100,"<>Từ chối") -> 0 | G11: =IFERROR(__xludf.DUMMYFUNCTION("IFERROR(INDEX(FILTER(Registrations!$D$2:$D100,Registrations!$H$2:$H100=$C11,Registrations!$L$2:$L100<>""Hủy"",Registrations!$L$2:$L100<>""Từ chối""),1),"""")"),"") | H11: =IFERROR(__xludf.DUMMYFUNCTION("IFERROR(INDEX(FILTER(Registrations!$E$2:$E100,Registrations!$H$2:$H100=$C11,Registrations!$L$2:$L100<>""Hủy"",Registrations!$L$2:$L100<>""Từ chối""),1),"""")"),"") | I11: =IFERROR(__xludf.DUMMYFUNCTION("IF(F11=0,"""",IF(IFERROR(INDEX(FILTER(Registrations!$F$2:$F100,Registrations!$H$2:$H100=$C11,Registrations!$L$2:$L100<>""Hủy"",Registrations!$L$2:$L100<>""Từ chối""),1),"""")=$A11,""Khớp"",""Sai kho""))"),"") | J11: B | K11: 9975000
A12: AYC | B12: 11 | C12: #011 | D12: 75QNED86BSA.ATV | E12: =IF(F12=0,"Còn trống",IF(F12=1,"Đã đăng ký","Trùng đăng ký")) -> Còn trống | F12: =COUNTIFS(Registrations!$H$2:$H100,$C12,Registrations!$L$2:$L100,"<>Hủy",Registrations!$L$2:$L100,"<>Từ chối") -> 0 | G12: =IFERROR(__xludf.DUMMYFUNCTION("IFERROR(INDEX(FILTER(Registrations!$D$2:$D100,Registrations!$H$2:$H100=$C12,Registrations!$L$2:$L100<>""Hủy"",Registrations!$L$2:$L100<>""Từ chối""),1),"""")"),"") | H12: =IFERROR(__xludf.DUMMYFUNCTION("IFERROR(INDEX(FILTER(Registrations!$E$2:$E100,Registrations!$H$2:$H100=$C12,Registrations!$L$2:$L100<>""Hủy"",Registrations!$L$2:$L100<>""Từ chối""),1),"""")"),"") | I12: =IFERROR(__xludf.DUMMYFUNCTION("IF(F12=0,"""",IF(IFERROR(INDEX(FILTER(Registrations!$F$2:$F100,Registrations!$H$2:$H100=$C12,Registrations!$L$2:$L100<>""Hủy"",Registrations!$L$2:$L100<>""Từ chối""),1),"""")=$A12,""Khớp"",""Sai kho""))"),"") | J12: B | K12: 10475000
A13: AYC | B13: 12 | C13: #012 | D13: 75QNED9MASA.AGAFLHX | E13: =IF(F13=0,"Còn trống",IF(F13=1,"Đã đăng ký","Trùng đăng ký")) -> Còn trống | F13: =COUNTIFS(Registrations!$H$2:$H100,$C13,Registrations!$L$2:$L100,"<>Hủy",Registrations!$L$2:$L100,"<>Từ chối") -> 0 | G13: =IFERROR(__xludf.DUMMYFUNCTION("IFERROR(INDEX(FILTER(Registrations!$D$2:$D100,Registrations!$H$2:$H100=$C13,Registrations!$L$2:$L100<>""Hủy"",Registrations!$L$2:$L100<>""Từ chối""),1),"""")"),"") | H13: =IFERROR(__xludf.DUMMYFUNCTION("IFERROR(INDEX(FILTER(Registrations!$E$2:$E100,Registrations!$H$2:$H100=$C13,Registrations!$L$2:$L100<>""Hủy"",Registrations!$L$2:$L100<>""Từ chối""),1),"""")"),"") | I13: =IFERROR(__xludf.DUMMYFUNCTION("IF(F13=0,"""",IF(IFERROR(INDEX(FILTER(Registrations!$F$2:$F100,Registrations!$H$2:$H100=$C13,Registrations!$L$2:$L100<>""Hủy"",Registrations!$L$2:$L100<>""Từ chối""),1),"""")=$A13,""Khớp"",""Sai kho""))"),"") | J13: B | K13: 12475000
A14: AYC | B14: 13 | C14: #013 | D14: OLED65G5PSA.ATV | E14: =IF(F14=0,"Còn trống",IF(F14=1,"Đã đăng ký","Trùng đăng ký")) -> Còn trống | F14: =COUNTIFS(Registrations!$H$2:$H100,$C14,Registrations!$L$2:$L100,"<>Hủy",Registrations!$L$2:$L100,"<>Từ chối") -> 0 | G14: =IFERROR(__xludf.DUMMYFUNCTION("IFERROR(INDEX(FILTER(Registrations!$D$2:$D100,Registrations!$H$2:$H100=$C14,Registrations!$L$2:$L100<>""Hủy"",Registrations!$L$2:$L100<>""Từ chối""),1),"""")"),"") | H14: =IFERROR(__xludf.DUMMYFUNCTION("IFERROR(INDEX(FILTER(Registrations!$E$2:$E100,Registrations!$H$2:$H100=$C14,Registrations!$L$2:$L100<>""Hủy"",Registrations!$L$2:$L100<>""Từ chối""),1),"""")"),"") | I14: =IFERROR(__xludf.DUMMYFUNCTION("IF(F14=0,"""",IF(IFERROR(INDEX(FILTER(Registrations!$F$2:$F100,Registrations!$H$2:$H100=$C14,Registrations!$L$2:$L100<>""Hủy"",Registrations!$L$2:$L100<>""Từ chối""),1),"""")=$A14,""Khớp"",""Sai kho""))"),"") | J14: B | K14: 17622500
A15: AYC | B15: 14 | C15: #014 | D15: OLED77C44LA.AEUQLHX | E15: =IF(F15=0,"Còn trống",IF(F15=1,"Đã đăng ký","Trùng đăng ký")) -> Còn trống | F15: =COUNTIFS(Registrations!$H$2:$H100,$C15,Registrations!$L$2:$L100,"<>Hủy",Registrations!$L$2:$L100,"<>Từ chối") -> 0 | G15: =IFERROR(__xludf.DUMMYFUNCTION("IFERROR(INDEX(FILTER(Registrations!$D$2:$D100,Registrations!$H$2:$H100=$C15,Registrations!$L$2:$L100<>""Hủy"",Registrations!$L$2:$L100<>""Từ chối""),1),"""")"),"") | H15: =IFERROR(__xludf.DUMMYFUNCTION("IFERROR(INDEX(FILTER(Registrations!$E$2:$E100,Registrations!$H$2:$H100=$C15,Registrations!$L$2:$L100<>""Hủy"",Registrations!$L$2:$L100<>""Từ chối""),1),"""")"),"") | I15: =IFERROR(__xludf.DUMMYFUNCTION("IF(F15=0,"""",IF(IFERROR(INDEX(FILTER(Registrations!$F$2:$F100,Registrations!$H$2:$H100=$C15,Registrations!$L$2:$L100<>""Hủy"",Registrations!$L$2:$L100<>""Từ chối""),1),"""")=$A15,""Khớp"",""Sai kho""))"),"") | J15: B | K15: 13975000
A16: AYC | B16: 15 | C16: #015 | D16: OLED77C54LA.AEUQLHX | E16: =IF(F16=0,"Còn trống",IF(F16=1,"Đã đăng ký","Trùng đăng ký")) -> Còn trống | F16: =COUNTIFS(Registrations!$H$2:$H100,$C16,Registrations!$L$2:$L100,"<>Hủy",Registrations!$L$2:$L100,"<>Từ chối") -> 0 | G16: =IFERROR(__xludf.DUMMYFUNCTION("IFERROR(INDEX(FILTER(Registrations!$D$2:$D100,Registrations!$H$2:$H100=$C16,Registrations!$L$2:$L100<>""Hủy"",Registrations!$L$2:$L100<>""Từ chối""),1),"""")"),"") | H16: =IFERROR(__xludf.DUMMYFUNCTION("IFERROR(INDEX(FILTER(Registrations!$E$2:$E100,Registrations!$H$2:$H100=$C16,Registrations!$L$2:$L100<>""Hủy"",Registrations!$L$2:$L100<>""Từ chối""),1),"""")"),"") | I16: =IFERROR(__xludf.DUMMYFUNCTION("IF(F16=0,"""",IF(IFERROR(INDEX(FILTER(Registrations!$F$2:$F100,Registrations!$H$2:$H100=$C16,Registrations!$L$2:$L100<>""Hủy"",Registrations!$L$2:$L100<>""Từ chối""),1),"""")=$A16,""Khớp"",""Sai kho""))"),"") | J16: B | K16: 14975000
A17: AYC | B17: 16 | C17: #016 | D17: OLED83B5PSA.AGAQLHX | E17: =IF(F17=0,"Còn trống",IF(F17=1,"Đã đăng ký","Trùng đăng ký")) -> Còn trống | F17: =COUNTIFS(Registrations!$H$2:$H100,$C17,Registrations!$L$2:$L100,"<>Hủy",Registrations!$L$2:$L100,"<>Từ chối") -> 0 | G17: =IFERROR(__xludf.DUMMYFUNCTION("IFERROR(INDEX(FILTER(Registrations!$D$2:$D100,Registrations!$H$2:$H100=$C17,Registrations!$L$2:$L100<>""Hủy"",Registrations!$L$2:$L100<>""Từ chối""),1),"""")"),"") | H17: =IFERROR(__xludf.DUMMYFUNCTION("IFERROR(INDEX(FILTER(Registrations!$E$2:$E100,Registrations!$H$2:$H100=$C17,Registrations!$L$2:$L100<>""Hủy"",Registrations!$L$2:$L100<>""Từ chối""),1),"""")"),"") | I17: =IFERROR(__xludf.DUMMYFUNCTION("IF(F17=0,"""",IF(IFERROR(INDEX(FILTER(Registrations!$F$2:$F100,Registrations!$H$2:$H100=$C17,Registrations!$L$2:$L100<>""Hủy"",Registrations!$L$2:$L100<>""Từ chối""),1),"""")=$A17,""Khớp"",""Sai kho""))"),"") | J17: B | K17: 16475000
A18: AYC | B18: 17 | C18: #017 | D18: OLED83M4PUA.AUSYLHX | E18: =IF(F18=0,"Còn trống",IF(F18=1,"Đã đăng ký","Trùng đăng ký")) -> Còn trống | F18: =COUNTIFS(Registrations!$H$2:$H100,$C18,Registrations!$L$2:$L100,"<>Hủy",Registrations!$L$2:$L100,"<>Từ chối") -> 0 | G18: =IFERROR(__xludf.DUMMYFUNCTION("IFERROR(INDEX(FILTER(Registrations!$D$2:$D100,Registrations!$H$2:$H100=$C18,Registrations!$L$2:$L100<>""Hủy"",Registrations!$L$2:$L100<>""Từ chối""),1),"""")"),"") | H18: =IFERROR(__xludf.DUMMYFUNCTION("IFERROR(INDEX(FILTER(Registrations!$E$2:$E100,Registrations!$H$2:$H100=$C18,Registrations!$L$2:$L100<>""Hủy"",Registrations!$L$2:$L100<>""Từ chối""),1),"""")"),"") | I18: =IFERROR(__xludf.DUMMYFUNCTION("IF(F18=0,"""",IF(IFERROR(INDEX(FILTER(Registrations!$F$2:$F100,Registrations!$H$2:$H100=$C18,Registrations!$L$2:$L100<>""Hủy"",Registrations!$L$2:$L100<>""Từ chối""),1),"""")=$A18,""Khớp"",""Sai kho""))"),"") | J18: B | K18: 17475000
A19: AYC | B19: 18 | C19: #018 | D19: OLED97M5PSA.AAU | E19: =IF(F19=0,"Còn trống",IF(F19=1,"Đã đăng ký","Trùng đăng ký")) -> Còn trống | F19: =COUNTIFS(Registrations!$H$2:$H100,$C19,Registrations!$L$2:$L100,"<>Hủy",Registrations!$L$2:$L100,"<>Từ chối") -> 0 | G19: =IFERROR(__xludf.DUMMYFUNCTION("IFERROR(INDEX(FILTER(Registrations!$D$2:$D100,Registrations!$H$2:$H100=$C19,Registrations!$L$2:$L100<>""Hủy"",Registrations!$L$2:$L100<>""Từ chối""),1),"""")"),"") | H19: =IFERROR(__xludf.DUMMYFUNCTION("IFERROR(INDEX(FILTER(Registrations!$E$2:$E100,Registrations!$H$2:$H100=$C19,Registrations!$L$2:$L100<>""Hủy"",Registrations!$L$2:$L100<>""Từ chối""),1),"""")"),"") | I19: =IFERROR(__xludf.DUMMYFUNCTION("IF(F19=0,"""",IF(IFERROR(INDEX(FILTER(Registrations!$F$2:$F100,Registrations!$H$2:$H100=$C19,Registrations!$L$2:$L100<>""Hủy"",Registrations!$L$2:$L100<>""Từ chối""),1),"""")=$A19,""Khớp"",""Sai kho""))"),"") | J19: B | K19: 25000000
A20: AYC | B20: 19 | C20: #019 | D20: OLED77C6PJA.AJLQLHX | E20: =IF(F20=0,"Còn trống",IF(F20=1,"Đã đăng ký","Trùng đăng ký")) -> Còn trống | F20: =COUNTIFS(Registrations!$H$2:$H100,$C20,Registrations!$L$2:$L100,"<>Hủy",Registrations!$L$2:$L100,"<>Từ chối") -> 0 | G20: =IFERROR(__xludf.DUMMYFUNCTION("IFERROR(INDEX(FILTER(Registrations!$D$2:$D100,Registrations!$H$2:$H100=$C20,Registrations!$L$2:$L100<>""Hủy"",Registrations!$L$2:$L100<>""Từ chối""),1),"""")"),"") | H20: =IFERROR(__xludf.DUMMYFUNCTION("IFERROR(INDEX(FILTER(Registrations!$E$2:$E100,Registrations!$H$2:$H100=$C20,Registrations!$L$2:$L100<>""Hủy"",Registrations!$L$2:$L100<>""Từ chối""),1),"""")"),"") | I20: =IFERROR(__xludf.DUMMYFUNCTION("IF(F20=0,"""",IF(IFERROR(INDEX(FILTER(Registrations!$F$2:$F100,Registrations!$H$2:$H100=$C20,Registrations!$L$2:$L100<>""Hủy"",Registrations!$L$2:$L100<>""Từ chối""),1),"""")=$A20,""Khớp"",""Sai kho""))"),"") | J20: GoodSet | K20: 17950000
A21: AYC | B21: 20 | C21: #020 | D21: OLED77B6PCA.ACNQLHX | E21: =IF(F21=0,"Còn trống",IF(F21=1,"Đã đăng ký","Trùng đăng ký")) -> Còn trống | F21: =COUNTIFS(Registrations!$H$2:$H100,$C21,Registrations!$L$2:$L100,"<>Hủy",Registrations!$L$2:$L100,"<>Từ chối") -> 0 | G21: =IFERROR(__xludf.DUMMYFUNCTION("IFERROR(INDEX(FILTER(Registrations!$D$2:$D100,Registrations!$H$2:$H100=$C21,Registrations!$L$2:$L100<>""Hủy"",Registrations!$L$2:$L100<>""Từ chối""),1),"""")"),"") | H21: =IFERROR(__xludf.DUMMYFUNCTION("IFERROR(INDEX(FILTER(Registrations!$E$2:$E100,Registrations!$H$2:$H100=$C21,Registrations!$L$2:$L100<>""Hủy"",Registrations!$L$2:$L100<>""Từ chối""),1),"""")"),"") | I21: =IFERROR(__xludf.DUMMYFUNCTION("IF(F21=0,"""",IF(IFERROR(INDEX(FILTER(Registrations!$F$2:$F100,Registrations!$H$2:$H100=$C21,Registrations!$L$2:$L100<>""Hủy"",Registrations!$L$2:$L100<>""Từ chối""),1),"""")=$A21,""Khớp"",""Sai kho""))"),"") | J21: GoodSet | K21: 13450000
A22: AYC | B22: 21 | C22: #021 | D22: 75QNED70BSA.AGAFLHX | E22: =IF(F22=0,"Còn trống",IF(F22=1,"Đã đăng ký","Trùng đăng ký")) -> Còn trống | F22: =COUNTIFS(Registrations!$H$2:$H100,$C22,Registrations!$L$2:$L100,"<>Hủy",Registrations!$L$2:$L100,"<>Từ chối") -> 0 | G22: =IFERROR(__xludf.DUMMYFUNCTION("IFERROR(INDEX(FILTER(Registrations!$D$2:$D100,Registrations!$H$2:$H100=$C22,Registrations!$L$2:$L100<>""Hủy"",Registrations!$L$2:$L100<>""Từ chối""),1),"""")"),"") | H22: =IFERROR(__xludf.DUMMYFUNCTION("IFERROR(INDEX(FILTER(Registrations!$E$2:$E100,Registrations!$H$2:$H100=$C22,Registrations!$L$2:$L100<>""Hủy"",Registrations!$L$2:$L100<>""Từ chối""),1),"""")"),"") | I22: =IFERROR(__xludf.DUMMYFUNCTION("IF(F22=0,"""",IF(IFERROR(INDEX(FILTER(Registrations!$F$2:$F100,Registrations!$H$2:$H100=$C22,Registrations!$L$2:$L100<>""Hủy"",Registrations!$L$2:$L100<>""Từ chối""),1),"""")=$A22,""Khớp"",""Sai kho""))"),"") | J22: GoodSet | K22: 8450000
A23: AYC | B23: 22 | C23: #022 | D23: 75QNED81B6A.AEUNLHX | E23: =IF(F23=0,"Còn trống",IF(F23=1,"Đã đăng ký","Trùng đăng ký")) -> Còn trống | F23: =COUNTIFS(Registrations!$H$2:$H100,$C23,Registrations!$L$2:$L100,"<>Hủy",Registrations!$L$2:$L100,"<>Từ chối") -> 0 | G23: =IFERROR(__xludf.DUMMYFUNCTION("IFERROR(INDEX(FILTER(Registrations!$D$2:$D100,Registrations!$H$2:$H100=$C23,Registrations!$L$2:$L100<>""Hủy"",Registrations!$L$2:$L100<>""Từ chối""),1),"""")"),"") | H23: =IFERROR(__xludf.DUMMYFUNCTION("IFERROR(INDEX(FILTER(Registrations!$E$2:$E100,Registrations!$H$2:$H100=$C23,Registrations!$L$2:$L100<>""Hủy"",Registrations!$L$2:$L100<>""Từ chối""),1),"""")"),"") | I23: =IFERROR(__xludf.DUMMYFUNCTION("IF(F23=0,"""",IF(IFERROR(INDEX(FILTER(Registrations!$F$2:$F100,Registrations!$H$2:$H100=$C23,Registrations!$L$2:$L100<>""Hủy"",Registrations!$L$2:$L100<>""Từ chối""),1),"""")=$A23,""Khớp"",""Sai kho""))"),"") | J23: GoodSet | K23: 9450000
A24: AYC | B24: 23 | C24: #023 | D24: 65NU850BPUA.AUSFLHX | E24: =IF(F24=0,"Còn trống",IF(F24=1,"Đã đăng ký","Trùng đăng ký")) -> Còn trống | F24: =COUNTIFS(Registrations!$H$2:$H100,$C24,Registrations!$L$2:$L100,"<>Hủy",Registrations!$L$2:$L100,"<>Từ chối") -> 0 | G24: =IFERROR(__xludf.DUMMYFUNCTION("IFERROR(INDEX(FILTER(Registrations!$D$2:$D100,Registrations!$H$2:$H100=$C24,Registrations!$L$2:$L100<>""Hủy"",Registrations!$L$2:$L100<>""Từ chối""),1),"""")"),"") | H24: =IFERROR(__xludf.DUMMYFUNCTION("IFERROR(INDEX(FILTER(Registrations!$E$2:$E100,Registrations!$H$2:$H100=$C24,Registrations!$L$2:$L100<>""Hủy"",Registrations!$L$2:$L100<>""Từ chối""),1),"""")"),"") | I24: =IFERROR(__xludf.DUMMYFUNCTION("IF(F24=0,"""",IF(IFERROR(INDEX(FILTER(Registrations!$F$2:$F100,Registrations!$H$2:$H100=$C24,Registrations!$L$2:$L100<>""Hủy"",Registrations!$L$2:$L100<>""Từ chối""),1),"""")=$A24,""Khớp"",""Sai kho""))"),"") | J24: GoodSet | K24: 6950000
A25: AYC | B25: 24 | C25: #024 | D25: 75MRGB86BSA.AGADLHX | E25: =IF(F25=0,"Còn trống",IF(F25=1,"Đã đăng ký","Trùng đăng ký")) -> Còn trống | F25: =COUNTIFS(Registrations!$H$2:$H100,$C25,Registrations!$L$2:$L100,"<>Hủy",Registrations!$L$2:$L100,"<>Từ chối") -> 0 | G25: =IFERROR(__xludf.DUMMYFUNCTION("IFERROR(INDEX(FILTER(Registrations!$D$2:$D100,Registrations!$H$2:$H100=$C25,Registrations!$L$2:$L100<>""Hủy"",Registrations!$L$2:$L100<>""Từ chối""),1),"""")"),"") | H25: =IFERROR(__xludf.DUMMYFUNCTION("IFERROR(INDEX(FILTER(Registrations!$E$2:$E100,Registrations!$H$2:$H100=$C25,Registrations!$L$2:$L100<>""Hủy"",Registrations!$L$2:$L100<>""Từ chối""),1),"""")"),"") | I25: =IFERROR(__xludf.DUMMYFUNCTION("IF(F25=0,"""",IF(IFERROR(INDEX(FILTER(Registrations!$F$2:$F100,Registrations!$H$2:$H100=$C25,Registrations!$L$2:$L100<>""Hủy"",Registrations!$L$2:$L100<>""Từ chối""),1),"""")=$A25,""Khớp"",""Sai kho""))"),"") | J25: GoodSet | K25: 17450000
A26: AYA | B26: 25 | C26: #025 | D26: 100QNED89AS.AGAFLHX | E26: =IF(F26=0,"Còn trống",IF(F26=1,"Đã đăng ký","Trùng đăng ký")) -> Còn trống | F26: =COUNTIFS(Registrations!$H$2:$H100,$C26,Registrations!$L$2:$L100,"<>Hủy",Registrations!$L$2:$L100,"<>Từ chối") -> 0 | G26: =IFERROR(__xludf.DUMMYFUNCTION("IFERROR(INDEX(FILTER(Registrations!$D$2:$D100,Registrations!$H$2:$H100=$C26,Registrations!$L$2:$L100<>""Hủy"",Registrations!$L$2:$L100<>""Từ chối""),1),"""")"),"") | H26: =IFERROR(__xludf.DUMMYFUNCTION("IFERROR(INDEX(FILTER(Registrations!$E$2:$E100,Registrations!$H$2:$H100=$C26,Registrations!$L$2:$L100<>""Hủy"",Registrations!$L$2:$L100<>""Từ chối""),1),"""")"),"") | I26: =IFERROR(__xludf.DUMMYFUNCTION("IF(F26=0,"""",IF(IFERROR(INDEX(FILTER(Registrations!$F$2:$F100,Registrations!$H$2:$H100=$C26,Registrations!$L$2:$L100<>""Hủy"",Registrations!$L$2:$L100<>""Từ chối""),1),"""")=$A26,""Khớp"",""Sai kho""))"),"") | J26: B | K26: 22475000
A27: AYA | B27: 26 | C27: #026 | D27: 27LX6TDGA.ATV | E27: =IF(F27=0,"Còn trống",IF(F27=1,"Đã đăng ký","Trùng đăng ký")) -> Còn trống | F27: =COUNTIFS(Registrations!$H$2:$H100,$C27,Registrations!$L$2:$L100,"<>Hủy",Registrations!$L$2:$L100,"<>Từ chối") -> 0 | G27: =IFERROR(__xludf.DUMMYFUNCTION("IFERROR(INDEX(FILTER(Registrations!$D$2:$D100,Registrations!$H$2:$H100=$C27,Registrations!$L$2:$L100<>""Hủy"",Registrations!$L$2:$L100<>""Từ chối""),1),"""")"),"") | H27: =IFERROR(__xludf.DUMMYFUNCTION("IFERROR(INDEX(FILTER(Registrations!$E$2:$E100,Registrations!$H$2:$H100=$C27,Registrations!$L$2:$L100<>""Hủy"",Registrations!$L$2:$L100<>""Từ chối""),1),"""")"),"") | I27: =IFERROR(__xludf.DUMMYFUNCTION("IF(F27=0,"""",IF(IFERROR(INDEX(FILTER(Registrations!$F$2:$F100,Registrations!$H$2:$H100=$C27,Registrations!$L$2:$L100<>""Hủy"",Registrations!$L$2:$L100<>""Từ chối""),1),"""")=$A27,""Khớp"",""Sai kho""))"),"") | J27: B | K27: 5085000
A28: AYA | B28: 27 | C28: #027 | D28: 27LX6TDGA.ATV | E28: =IF(F28=0,"Còn trống",IF(F28=1,"Đã đăng ký","Trùng đăng ký")) -> Còn trống | F28: =COUNTIFS(Registrations!$H$2:$H100,$C28,Registrations!$L$2:$L100,"<>Hủy",Registrations!$L$2:$L100,"<>Từ chối") -> 0 | G28: =IFERROR(__xludf.DUMMYFUNCTION("IFERROR(INDEX(FILTER(Registrations!$D$2:$D100,Registrations!$H$2:$H100=$C28,Registrations!$L$2:$L100<>""Hủy"",Registrations!$L$2:$L100<>""Từ chối""),1),"""")"),"") | H28: =IFERROR(__xludf.DUMMYFUNCTION("IFERROR(INDEX(FILTER(Registrations!$E$2:$E100,Registrations!$H$2:$H100=$C28,Registrations!$L$2:$L100<>""Hủy"",Registrations!$L$2:$L100<>""Từ chối""),1),"""")"),"") | I28: =IFERROR(__xludf.DUMMYFUNCTION("IF(F28=0,"""",IF(IFERROR(INDEX(FILTER(Registrations!$F$2:$F100,Registrations!$H$2:$H100=$C28,Registrations!$L$2:$L100<>""Hủy"",Registrations!$L$2:$L100<>""Từ chối""),1),"""")=$A28,""Khớp"",""Sai kho""))"),"") | J28: B | K28: 5085000
A29: AYA | B29: 28 | C29: #028 | D29: 27LX6TDGA.ATV | E29: =IF(F29=0,"Còn trống",IF(F29=1,"Đã đăng ký","Trùng đăng ký")) -> Còn trống | F29: =COUNTIFS(Registrations!$H$2:$H100,$C29,Registrations!$L$2:$L100,"<>Hủy",Registrations!$L$2:$L100,"<>Từ chối") -> 0 | G29: =IFERROR(__xludf.DUMMYFUNCTION("IFERROR(INDEX(FILTER(Registrations!$D$2:$D100,Registrations!$H$2:$H100=$C29,Registrations!$L$2:$L100<>""Hủy"",Registrations!$L$2:$L100<>""Từ chối""),1),"""")"),"") | H29: =IFERROR(__xludf.DUMMYFUNCTION("IFERROR(INDEX(FILTER(Registrations!$E$2:$E100,Registrations!$H$2:$H100=$C29,Registrations!$L$2:$L100<>""Hủy"",Registrations!$L$2:$L100<>""Từ chối""),1),"""")"),"") | I29: =IFERROR(__xludf.DUMMYFUNCTION("IF(F29=0,"""",IF(IFERROR(INDEX(FILTER(Registrations!$F$2:$F100,Registrations!$H$2:$H100=$C29,Registrations!$L$2:$L100<>""Hủy"",Registrations!$L$2:$L100<>""Từ chối""),1),"""")=$A29,""Khớp"",""Sai kho""))"),"") | J29: B | K29: 5085000
A30: AYA | B30: 29 | C30: #029 | D30: 43LB6500PSB.AWZSLHX | E30: =IF(F30=0,"Còn trống",IF(F30=1,"Đã đăng ký","Trùng đăng ký")) -> Còn trống | F30: =COUNTIFS(Registrations!$H$2:$H100,$C30,Registrations!$L$2:$L100,"<>Hủy",Registrations!$L$2:$L100,"<>Từ chối") -> 0 | G30: =IFERROR(__xludf.DUMMYFUNCTION("IFERROR(INDEX(FILTER(Registrations!$D$2:$D100,Registrations!$H$2:$H100=$C30,Registrations!$L$2:$L100<>""Hủy"",Registrations!$L$2:$L100<>""Từ chối""),1),"""")"),"") | H30: =IFERROR(__xludf.DUMMYFUNCTION("IFERROR(INDEX(FILTER(Registrations!$E$2:$E100,Registrations!$H$2:$H100=$C30,Registrations!$L$2:$L100<>""Hủy"",Registrations!$L$2:$L100<>""Từ chối""),1),"""")"),"") | I30: =IFERROR(__xludf.DUMMYFUNCTION("IF(F30=0,"""",IF(IFERROR(INDEX(FILTER(Registrations!$F$2:$F100,Registrations!$H$2:$H100=$C30,Registrations!$L$2:$L100<>""Hủy"",Registrations!$L$2:$L100<>""Từ chối""),1),"""")=$A30,""Khớp"",""Sai kho""))"),"") | J30: B | K30: 903500
A31: AYA | B31: 30 | C31: #030 | D31: 65UA8055PSA.ATV | E31: =IF(F31=0,"Còn trống",IF(F31=1,"Đã đăng ký","Trùng đăng ký")) -> Còn trống | F31: =COUNTIFS(Registrations!$H$2:$H100,$C31,Registrations!$L$2:$L100,"<>Hủy",Registrations!$L$2:$L100,"<>Từ chối") -> 0 | G31: =IFERROR(__xludf.DUMMYFUNCTION("IFERROR(INDEX(FILTER(Registrations!$D$2:$D100,Registrations!$H$2:$H100=$C31,Registrations!$L$2:$L100<>""Hủy"",Registrations!$L$2:$L100<>""Từ chối""),1),"""")"),"") | H31: =IFERROR(__xludf.DUMMYFUNCTION("IFERROR(INDEX(FILTER(Registrations!$E$2:$E100,Registrations!$H$2:$H100=$C31,Registrations!$L$2:$L100<>""Hủy"",Registrations!$L$2:$L100<>""Từ chối""),1),"""")"),"") | I31: =IFERROR(__xludf.DUMMYFUNCTION("IF(F31=0,"""",IF(IFERROR(INDEX(FILTER(Registrations!$F$2:$F100,Registrations!$H$2:$H100=$C31,Registrations!$L$2:$L100<>""Hủy"",Registrations!$L$2:$L100<>""Từ chối""),1),"""")=$A31,""Khớp"",""Sai kho""))"),"") | J31: A | K31: 4872500
A32: AYA | B32: 31 | C32: #031 | D32: 75QNED86ASA.ATV | E32: =IF(F32=0,"Còn trống",IF(F32=1,"Đã đăng ký","Trùng đăng ký")) -> Còn trống | F32: =COUNTIFS(Registrations!$H$2:$H100,$C32,Registrations!$L$2:$L100,"<>Hủy",Registrations!$L$2:$L100,"<>Từ chối") -> 0 | G32: =IFERROR(__xludf.DUMMYFUNCTION("IFERROR(INDEX(FILTER(Registrations!$D$2:$D100,Registrations!$H$2:$H100=$C32,Registrations!$L$2:$L100<>""Hủy"",Registrations!$L$2:$L100<>""Từ chối""),1),"""")"),"") | H32: =IFERROR(__xludf.DUMMYFUNCTION("IFERROR(INDEX(FILTER(Registrations!$E$2:$E100,Registrations!$H$2:$H100=$C32,Registrations!$L$2:$L100<>""Hủy"",Registrations!$L$2:$L100<>""Từ chối""),1),"""")"),"") | I32: =IFERROR(__xludf.DUMMYFUNCTION("IF(F32=0,"""",IF(IFERROR(INDEX(FILTER(Registrations!$F$2:$F100,Registrations!$H$2:$H100=$C32,Registrations!$L$2:$L100<>""Hủy"",Registrations!$L$2:$L100<>""Từ chối""),1),"""")=$A32,""Khớp"",""Sai kho""))"),"") | J32: B | K32: 10022500
A33: AYA | B33: 32 | C33: #032 | D33: 75QNED9MASA.AGAFLHX | E33: =IF(F33=0,"Còn trống",IF(F33=1,"Đã đăng ký","Trùng đăng ký")) -> Còn trống | F33: =COUNTIFS(Registrations!$H$2:$H100,$C33,Registrations!$L$2:$L100,"<>Hủy",Registrations!$L$2:$L100,"<>Từ chối") -> 0 | G33: =IFERROR(__xludf.DUMMYFUNCTION("IFERROR(INDEX(FILTER(Registrations!$D$2:$D100,Registrations!$H$2:$H100=$C33,Registrations!$L$2:$L100<>""Hủy"",Registrations!$L$2:$L100<>""Từ chối""),1),"""")"),"") | H33: =IFERROR(__xludf.DUMMYFUNCTION("IFERROR(INDEX(FILTER(Registrations!$E$2:$E100,Registrations!$H$2:$H100=$C33,Registrations!$L$2:$L100<>""Hủy"",Registrations!$L$2:$L100<>""Từ chối""),1),"""")"),"") | I33: =IFERROR(__xludf.DUMMYFUNCTION("IF(F33=0,"""",IF(IFERROR(INDEX(FILTER(Registrations!$F$2:$F100,Registrations!$H$2:$H100=$C33,Registrations!$L$2:$L100<>""Hủy"",Registrations!$L$2:$L100<>""Từ chối""),1),"""")=$A33,""Khớp"",""Sai kho""))"),"") | J33: B | K33: 12475000
A34: AYA | B34: 33 | C34: #033 | D34: OLED48B5PSA.ATV | E34: =IF(F34=0,"Còn trống",IF(F34=1,"Đã đăng ký","Trùng đăng ký")) -> Còn trống | F34: =COUNTIFS(Registrations!$H$2:$H100,$C34,Registrations!$L$2:$L100,"<>Hủy",Registrations!$L$2:$L100,"<>Từ chối") -> 0 | G34: =IFERROR(__xludf.DUMMYFUNCTION("IFERROR(INDEX(FILTER(Registrations!$D$2:$D100,Registrations!$H$2:$H100=$C34,Registrations!$L$2:$L100<>""Hủy"",Registrations!$L$2:$L100<>""Từ chối""),1),"""")"),"") | H34: =IFERROR(__xludf.DUMMYFUNCTION("IFERROR(INDEX(FILTER(Registrations!$E$2:$E100,Registrations!$H$2:$H100=$C34,Registrations!$L$2:$L100<>""Hủy"",Registrations!$L$2:$L100<>""Từ chối""),1),"""")"),"") | I34: =IFERROR(__xludf.DUMMYFUNCTION("IF(F34=0,"""",IF(IFERROR(INDEX(FILTER(Registrations!$F$2:$F100,Registrations!$H$2:$H100=$C34,Registrations!$L$2:$L100<>""Hủy"",Registrations!$L$2:$L100<>""Từ chối""),1),"""")=$A34,""Khớp"",""Sai kho""))"),"") | J34: B | K34: 7322500
A35: AYA | B35: 34 | C35: #034 | D35: OLED65G5PSA.ATV | E35: =IF(F35=0,"Còn trống",IF(F35=1,"Đã đăng ký","Trùng đăng ký")) -> Còn trống | F35: =COUNTIFS(Registrations!$H$2:$H100,$C35,Registrations!$L$2:$L100,"<>Hủy",Registrations!$L$2:$L100,"<>Từ chối") -> 0 | G35: =IFERROR(__xludf.DUMMYFUNCTION("IFERROR(INDEX(FILTER(Registrations!$D$2:$D100,Registrations!$H$2:$H100=$C35,Registrations!$L$2:$L100<>""Hủy"",Registrations!$L$2:$L100<>""Từ chối""),1),"""")"),"") | H35: =IFERROR(__xludf.DUMMYFUNCTION("IFERROR(INDEX(FILTER(Registrations!$E$2:$E100,Registrations!$H$2:$H100=$C35,Registrations!$L$2:$L100<>""Hủy"",Registrations!$L$2:$L100<>""Từ chối""),1),"""")"),"") | I35: =IFERROR(__xludf.DUMMYFUNCTION("IF(F35=0,"""",IF(IFERROR(INDEX(FILTER(Registrations!$F$2:$F100,Registrations!$H$2:$H100=$C35,Registrations!$L$2:$L100<>""Hủy"",Registrations!$L$2:$L100<>""Từ chối""),1),"""")=$A35,""Khớp"",""Sai kho""))"),"") | J35: B | K35: 17622500
A36: AYA | B36: 35 | C36: #035 | D36: OLED77C44LA.AEUQLHX | E36: =IF(F36=0,"Còn trống",IF(F36=1,"Đã đăng ký","Trùng đăng ký")) -> Còn trống | F36: =COUNTIFS(Registrations!$H$2:$H100,$C36,Registrations!$L$2:$L100,"<>Hủy",Registrations!$L$2:$L100,"<>Từ chối") -> 0 | G36: =IFERROR(__xludf.DUMMYFUNCTION("IFERROR(INDEX(FILTER(Registrations!$D$2:$D100,Registrations!$H$2:$H100=$C36,Registrations!$L$2:$L100<>""Hủy"",Registrations!$L$2:$L100<>""Từ chối""),1),"""")"),"") | H36: =IFERROR(__xludf.DUMMYFUNCTION("IFERROR(INDEX(FILTER(Registrations!$E$2:$E100,Registrations!$H$2:$H100=$C36,Registrations!$L$2:$L100<>""Hủy"",Registrations!$L$2:$L100<>""Từ chối""),1),"""")"),"") | I36: =IFERROR(__xludf.DUMMYFUNCTION("IF(F36=0,"""",IF(IFERROR(INDEX(FILTER(Registrations!$F$2:$F100,Registrations!$H$2:$H100=$C36,Registrations!$L$2:$L100<>""Hủy"",Registrations!$L$2:$L100<>""Từ chối""),1),"""")=$A36,""Khớp"",""Sai kho""))"),"") | J36: B | K36: 13975000
A37: AYA | B37: 36 | C37: #036 | D37: OLED77C54LA.AEUQLHX | E37: =IF(F37=0,"Còn trống",IF(F37=1,"Đã đăng ký","Trùng đăng ký")) -> Còn trống | F37: =COUNTIFS(Registrations!$H$2:$H100,$C37,Registrations!$L$2:$L100,"<>Hủy",Registrations!$L$2:$L100,"<>Từ chối") -> 0 | G37: =IFERROR(__xludf.DUMMYFUNCTION("IFERROR(INDEX(FILTER(Registrations!$D$2:$D100,Registrations!$H$2:$H100=$C37,Registrations!$L$2:$L100<>""Hủy"",Registrations!$L$2:$L100<>""Từ chối""),1),"""")"),"") | H37: =IFERROR(__xludf.DUMMYFUNCTION("IFERROR(INDEX(FILTER(Registrations!$E$2:$E100,Registrations!$H$2:$H100=$C37,Registrations!$L$2:$L100<>""Hủy"",Registrations!$L$2:$L100<>""Từ chối""),1),"""")"),"") | I37: =IFERROR(__xludf.DUMMYFUNCTION("IF(F37=0,"""",IF(IFERROR(INDEX(FILTER(Registrations!$F$2:$F100,Registrations!$H$2:$H100=$C37,Registrations!$L$2:$L100<>""Hủy"",Registrations!$L$2:$L100<>""Từ chối""),1),"""")=$A37,""Khớp"",""Sai kho""))"),"") | J37: B | K37: 14975000
A38: AYA | B38: 37 | C38: #037 | D38: OLED83B5PSA.AGAQLHX | E38: =IF(F38=0,"Còn trống",IF(F38=1,"Đã đăng ký","Trùng đăng ký")) -> Còn trống | F38: =COUNTIFS(Registrations!$H$2:$H100,$C38,Registrations!$L$2:$L100,"<>Hủy",Registrations!$L$2:$L100,"<>Từ chối") -> 0 | G38: =IFERROR(__xludf.DUMMYFUNCTION("IFERROR(INDEX(FILTER(Registrations!$D$2:$D100,Registrations!$H$2:$H100=$C38,Registrations!$L$2:$L100<>""Hủy"",Registrations!$L$2:$L100<>""Từ chối""),1),"""")"),"") | H38: =IFERROR(__xludf.DUMMYFUNCTION("IFERROR(INDEX(FILTER(Registrations!$E$2:$E100,Registrations!$H$2:$H100=$C38,Registrations!$L$2:$L100<>""Hủy"",Registrations!$L$2:$L100<>""Từ chối""),1),"""")"),"") | I38: =IFERROR(__xludf.DUMMYFUNCTION("IF(F38=0,"""",IF(IFERROR(INDEX(FILTER(Registrations!$F$2:$F100,Registrations!$H$2:$H100=$C38,Registrations!$L$2:$L100<>""Hủy"",Registrations!$L$2:$L100<>""Từ chối""),1),"""")=$A38,""Khớp"",""Sai kho""))"),"") | J38: B | K38: 16475000
A39: AYA | B39: 38 | C39: #038 | D39: OLED83C5PSA.AWZQLHX | E39: =IF(F39=0,"Còn trống",IF(F39=1,"Đã đăng ký","Trùng đăng ký")) -> Còn trống | F39: =COUNTIFS(Registrations!$H$2:$H100,$C39,Registrations!$L$2:$L100,"<>Hủy",Registrations!$L$2:$L100,"<>Từ chối") -> 0 | G39: =IFERROR(__xludf.DUMMYFUNCTION("IFERROR(INDEX(FILTER(Registrations!$D$2:$D100,Registrations!$H$2:$H100=$C39,Registrations!$L$2:$L100<>""Hủy"",Registrations!$L$2:$L100<>""Từ chối""),1),"""")"),"") | H39: =IFERROR(__xludf.DUMMYFUNCTION("IFERROR(INDEX(FILTER(Registrations!$E$2:$E100,Registrations!$H$2:$H100=$C39,Registrations!$L$2:$L100<>""Hủy"",Registrations!$L$2:$L100<>""Từ chối""),1),"""")"),"") | I39: =IFERROR(__xludf.DUMMYFUNCTION("IF(F39=0,"""",IF(IFERROR(INDEX(FILTER(Registrations!$F$2:$F100,Registrations!$H$2:$H100=$C39,Registrations!$L$2:$L100<>""Hủy"",Registrations!$L$2:$L100<>""Từ chối""),1),"""")=$A39,""Khớp"",""Sai kho""))"),"") | J39: B | K39: 17475000
A40: AYA | B40: 39 | C40: #039 | D40: OLED77C6PJA.AJLQLHX | E40: =IF(F40=0,"Còn trống",IF(F40=1,"Đã đăng ký","Trùng đăng ký")) -> Còn trống | F40: =COUNTIFS(Registrations!$H$2:$H100,$C40,Registrations!$L$2:$L100,"<>Hủy",Registrations!$L$2:$L100,"<>Từ chối") -> 0 | G40: =IFERROR(__xludf.DUMMYFUNCTION("IFERROR(INDEX(FILTER(Registrations!$D$2:$D100,Registrations!$H$2:$H100=$C40,Registrations!$L$2:$L100<>""Hủy"",Registrations!$L$2:$L100<>""Từ chối""),1),"""")"),"") | H40: =IFERROR(__xludf.DUMMYFUNCTION("IFERROR(INDEX(FILTER(Registrations!$E$2:$E100,Registrations!$H$2:$H100=$C40,Registrations!$L$2:$L100<>""Hủy"",Registrations!$L$2:$L100<>""Từ chối""),1),"""")"),"") | I40: =IFERROR(__xludf.DUMMYFUNCTION("IF(F40=0,"""",IF(IFERROR(INDEX(FILTER(Registrations!$F$2:$F100,Registrations!$H$2:$H100=$C40,Registrations!$L$2:$L100<>""Hủy"",Registrations!$L$2:$L100<>""Từ chối""),1),"""")=$A40,""Khớp"",""Sai kho""))"),"") | J40: GoodSet | K40: 17950000
A41: AYA | B41: 40 | C41: #040 | D41: 75QNED70BSA.AGAFLHX | E41: =IF(F41=0,"Còn trống",IF(F41=1,"Đã đăng ký","Trùng đăng ký")) -> Còn trống | F41: =COUNTIFS(Registrations!$H$2:$H100,$C41,Registrations!$L$2:$L100,"<>Hủy",Registrations!$L$2:$L100,"<>Từ chối") -> 0 | G41: =IFERROR(__xludf.DUMMYFUNCTION("IFERROR(INDEX(FILTER(Registrations!$D$2:$D100,Registrations!$H$2:$H100=$C41,Registrations!$L$2:$L100<>""Hủy"",Registrations!$L$2:$L100<>""Từ chối""),1),"""")"),"") | H41: =IFERROR(__xludf.DUMMYFUNCTION("IFERROR(INDEX(FILTER(Registrations!$E$2:$E100,Registrations!$H$2:$H100=$C41,Registrations!$L$2:$L100<>""Hủy"",Registrations!$L$2:$L100<>""Từ chối""),1),"""")"),"") | I41: =IFERROR(__xludf.DUMMYFUNCTION("IF(F41=0,"""",IF(IFERROR(INDEX(FILTER(Registrations!$F$2:$F100,Registrations!$H$2:$H100=$C41,Registrations!$L$2:$L100<>""Hủy"",Registrations!$L$2:$L100<>""Từ chối""),1),"""")=$A41,""Khớp"",""Sai kho""))"),"") | J41: GoodSet | K41: 8450000
A42: AYA | B42: 41 | C42: #041 | D42: 65NU850BPUA.AUSFLHX | E42: =IF(F42=0,"Còn trống",IF(F42=1,"Đã đăng ký","Trùng đăng ký")) -> Còn trống | F42: =COUNTIFS(Registrations!$H$2:$H100,$C42,Registrations!$L$2:$L100,"<>Hủy",Registrations!$L$2:$L100,"<>Từ chối") -> 0 | G42: =IFERROR(__xludf.DUMMYFUNCTION("IFERROR(INDEX(FILTER(Registrations!$D$2:$D100,Registrations!$H$2:$H100=$C42,Registrations!$L$2:$L100<>""Hủy"",Registrations!$L$2:$L100<>""Từ chối""),1),"""")"),"") | H42: =IFERROR(__xludf.DUMMYFUNCTION("IFERROR(INDEX(FILTER(Registrations!$E$2:$E100,Registrations!$H$2:$H100=$C42,Registrations!$L$2:$L100<>""Hủy"",Registrations!$L$2:$L100<>""Từ chối""),1),"""")"),"") | I42: =IFERROR(__xludf.DUMMYFUNCTION("IF(F42=0,"""",IF(IFERROR(INDEX(FILTER(Registrations!$F$2:$F100,Registrations!$H$2:$H100=$C42,Registrations!$L$2:$L100<>""Hủy"",Registrations!$L$2:$L100<>""Từ chối""),1),"""")=$A42,""Khớp"",""Sai kho""))"),"") | J42: GoodSet | K42: 6950000
A43: AYA | B43: 42 | C43: #042 | D43: 75MRGB86BSA.AGADLHX | E43: =IF(F43=0,"Còn trống",IF(F43=1,"Đã đăng ký","Trùng đăng ký")) -> Còn trống | F43: =COUNTIFS(Registrations!$H$2:$H100,$C43,Registrations!$L$2:$L100,"<>Hủy",Registrations!$L$2:$L100,"<>Từ chối") -> 0 | G43: =IFERROR(__xludf.DUMMYFUNCTION("IFERROR(INDEX(FILTER(Registrations!$D$2:$D100,Registrations!$H$2:$H100=$C43,Registrations!$L$2:$L100<>""Hủy"",Registrations!$L$2:$L100<>""Từ chối""),1),"""")"),"") | H43: =IFERROR(__xludf.DUMMYFUNCTION("IFERROR(INDEX(FILTER(Registrations!$E$2:$E100,Registrations!$H$2:$H100=$C43,Registrations!$L$2:$L100<>""Hủy"",Registrations!$L$2:$L100<>""Từ chối""),1),"""")"),"") | I43: =IFERROR(__xludf.DUMMYFUNCTION("IF(F43=0,"""",IF(IFERROR(INDEX(FILTER(Registrations!$F$2:$F100,Registrations!$H$2:$H100=$C43,Registrations!$L$2:$L100<>""Hủy"",Registrations!$L$2:$L100<>""Từ chối""),1),"""")=$A43,""Khớp"",""Sai kho""))"),"") | J43: GoodSet | K43: 17450000
A44: AYA | B44: 43 | C44: #043 | D44: OLED77G5PSA.ATV | E44: =IF(F44=0,"Còn trống",IF(F44=1,"Đã đăng ký","Trùng đăng ký")) -> Còn trống | F44: =COUNTIFS(Registrations!$H$2:$H100,$C44,Registrations!$L$2:$L100,"<>Hủy",Registrations!$L$2:$L100,"<>Từ chối") -> 0 | G44: =IFERROR(__xludf.DUMMYFUNCTION("IFERROR(INDEX(FILTER(Registrations!$D$2:$D100,Registrations!$H$2:$H100=$C44,Registrations!$L$2:$L100<>""Hủy"",Registrations!$L$2:$L100<>""Từ chối""),1),"""")"),"") | H44: =IFERROR(__xludf.DUMMYFUNCTION("IFERROR(INDEX(FILTER(Registrations!$E$2:$E100,Registrations!$H$2:$H100=$C44,Registrations!$L$2:$L100<>""Hủy"",Registrations!$L$2:$L100<>""Từ chối""),1),"""")"),"") | I44: =IFERROR(__xludf.DUMMYFUNCTION("IF(F44=0,"""",IF(IFERROR(INDEX(FILTER(Registrations!$F$2:$F100,Registrations!$H$2:$H100=$C44,Registrations!$L$2:$L100<>""Hủy"",Registrations!$L$2:$L100<>""Từ chối""),1),"""")=$A44,""Khớp"",""Sai kho""))"),"") | J44: GoodSet | K44: 58845000
A45: AYA | B45: 44 | C45: #044 | D45: 65QNED92ASA.ATV | E45: =IF(F45=0,"Còn trống",IF(F45=1,"Đã đăng ký","Trùng đăng ký")) -> Còn trống | F45: =COUNTIFS(Registrations!$H$2:$H100,$C45,Registrations!$L$2:$L100,"<>Hủy",Registrations!$L$2:$L100,"<>Từ chối") -> 0 | G45: =IFERROR(__xludf.DUMMYFUNCTION("IFERROR(INDEX(FILTER(Registrations!$D$2:$D100,Registrations!$H$2:$H100=$C45,Registrations!$L$2:$L100<>""Hủy"",Registrations!$L$2:$L100<>""Từ chối""),1),"""")"),"") | H45: =IFERROR(__xludf.DUMMYFUNCTION("IFERROR(INDEX(FILTER(Registrations!$E$2:$E100,Registrations!$H$2:$H100=$C45,Registrations!$L$2:$L100<>""Hủy"",Registrations!$L$2:$L100<>""Từ chối""),1),"""")"),"") | I45: =IFERROR(__xludf.DUMMYFUNCTION("IF(F45=0,"""",IF(IFERROR(INDEX(FILTER(Registrations!$F$2:$F100,Registrations!$H$2:$H100=$C45,Registrations!$L$2:$L100<>""Hủy"",Registrations!$L$2:$L100<>""Từ chối""),1),"""")=$A45,""Khớp"",""Sai kho""))"),"") | J45: GoodSet | K45: 18595000
A46: AYA | B46: 45 | C46: #045 | D46: 65QNED92ASA.ATV | E46: =IF(F46=0,"Còn trống",IF(F46=1,"Đã đăng ký","Trùng đăng ký")) -> Còn trống | F46: =COUNTIFS(Registrations!$H$2:$H100,$C46,Registrations!$L$2:$L100,"<>Hủy",Registrations!$L$2:$L100,"<>Từ chối") -> 0 | G46: =IFERROR(__xludf.DUMMYFUNCTION("IFERROR(INDEX(FILTER(Registrations!$D$2:$D100,Registrations!$H$2:$H100=$C46,Registrations!$L$2:$L100<>""Hủy"",Registrations!$L$2:$L100<>""Từ chối""),1),"""")"),"") | H46: =IFERROR(__xludf.DUMMYFUNCTION("IFERROR(INDEX(FILTER(Registrations!$E$2:$E100,Registrations!$H$2:$H100=$C46,Registrations!$L$2:$L100<>""Hủy"",Registrations!$L$2:$L100<>""Từ chối""),1),"""")"),"") | I46: =IFERROR(__xludf.DUMMYFUNCTION("IF(F46=0,"""",IF(IFERROR(INDEX(FILTER(Registrations!$F$2:$F100,Registrations!$H$2:$H100=$C46,Registrations!$L$2:$L100<>""Hủy"",Registrations!$L$2:$L100<>""Từ chối""),1),"""")=$A46,""Khớp"",""Sai kho""))"),"") | J46: GoodSet | K46: 18595000
A47: AYA | B47: 46 | C47: #046 | D47: 43QNED81ASA.ATV | E47: =IF(F47=0,"Còn trống",IF(F47=1,"Đã đăng ký","Trùng đăng ký")) -> Còn trống | F47: =COUNTIFS(Registrations!$H$2:$H100,$C47,Registrations!$L$2:$L100,"<>Hủy",Registrations!$L$2:$L100,"<>Từ chối") -> 0 | G47: =IFERROR(__xludf.DUMMYFUNCTION("IFERROR(INDEX(FILTER(Registrations!$D$2:$D100,Registrations!$H$2:$H100=$C47,Registrations!$L$2:$L100<>""Hủy"",Registrations!$L$2:$L100<>""Từ chối""),1),"""")"),"") | H47: =IFERROR(__xludf.DUMMYFUNCTION("IFERROR(INDEX(FILTER(Registrations!$E$2:$E100,Registrations!$H$2:$H100=$C47,Registrations!$L$2:$L100<>""Hủy"",Registrations!$L$2:$L100<>""Từ chối""),1),"""")"),"") | I47: =IFERROR(__xludf.DUMMYFUNCTION("IF(F47=0,"""",IF(IFERROR(INDEX(FILTER(Registrations!$F$2:$F100,Registrations!$H$2:$H100=$C47,Registrations!$L$2:$L100<>""Hủy"",Registrations!$L$2:$L100<>""Từ chối""),1),"""")=$A47,""Khớp"",""Sai kho""))"),"") | J47: GoodSet | K47: 7045000
A48: AYA | B48: 47 | C48: #047 | D48: 55QNED80ASA.ATV | E48: =IF(F48=0,"Còn trống",IF(F48=1,"Đã đăng ký","Trùng đăng ký")) -> Còn trống | F48: =COUNTIFS(Registrations!$H$2:$H100,$C48,Registrations!$L$2:$L100,"<>Hủy",Registrations!$L$2:$L100,"<>Từ chối") -> 0 | G48: =IFERROR(__xludf.DUMMYFUNCTION("IFERROR(INDEX(FILTER(Registrations!$D$2:$D100,Registrations!$H$2:$H100=$C48,Registrations!$L$2:$L100<>""Hủy"",Registrations!$L$2:$L100<>""Từ chối""),1),"""")"),"") | H48: =IFERROR(__xludf.DUMMYFUNCTION("IFERROR(INDEX(FILTER(Registrations!$E$2:$E100,Registrations!$H$2:$H100=$C48,Registrations!$L$2:$L100<>""Hủy"",Registrations!$L$2:$L100<>""Từ chối""),1),"""")"),"") | I48: =IFERROR(__xludf.DUMMYFUNCTION("IF(F48=0,"""",IF(IFERROR(INDEX(FILTER(Registrations!$F$2:$F100,Registrations!$H$2:$H100=$C48,Registrations!$L$2:$L100<>""Hủy"",Registrations!$L$2:$L100<>""Từ chối""),1),"""")=$A48,""Khớp"",""Sai kho""))"),"") | J48: GoodSet | K48: 9495000
A49: AYA | B49: 48 | C49: #048 | D49: 75NANO80ASA.ATV | E49: =IF(F49=0,"Còn trống",IF(F49=1,"Đã đăng ký","Trùng đăng ký")) -> Còn trống | F49: =COUNTIFS(Registrations!$H$2:$H100,$C49,Registrations!$L$2:$L100,"<>Hủy",Registrations!$L$2:$L100,"<>Từ chối") -> 0 | G49: =IFERROR(__xludf.DUMMYFUNCTION("IFERROR(INDEX(FILTER(Registrations!$D$2:$D100,Registrations!$H$2:$H100=$C49,Registrations!$L$2:$L100<>""Hủy"",Registrations!$L$2:$L100<>""Từ chối""),1),"""")"),"") | H49: =IFERROR(__xludf.DUMMYFUNCTION("IFERROR(INDEX(FILTER(Registrations!$E$2:$E100,Registrations!$H$2:$H100=$C49,Registrations!$L$2:$L100<>""Hủy"",Registrations!$L$2:$L100<>""Từ chối""),1),"""")"),"") | I49: =IFERROR(__xludf.DUMMYFUNCTION("IF(F49=0,"""",IF(IFERROR(INDEX(FILTER(Registrations!$F$2:$F100,Registrations!$H$2:$H100=$C49,Registrations!$L$2:$L100<>""Hủy"",Registrations!$L$2:$L100<>""Từ chối""),1),"""")=$A49,""Khớp"",""Sai kho""))"),"") | J49: GoodSet | K49: 15395000
A50: AYA | B50: 49 | C50: #049 | D50: 75NANO80ASA.ATV | E50: =IF(F50=0,"Còn trống",IF(F50=1,"Đã đăng ký","Trùng đăng ký")) -> Còn trống | F50: =COUNTIFS(Registrations!$H$2:$H100,$C50,Registrations!$L$2:$L100,"<>Hủy",Registrations!$L$2:$L100,"<>Từ chối") -> 0 | G50: =IFERROR(__xludf.DUMMYFUNCTION("IFERROR(INDEX(FILTER(Registrations!$D$2:$D100,Registrations!$H$2:$H100=$C50,Registrations!$L$2:$L100<>""Hủy"",Registrations!$L$2:$L100<>""Từ chối""),1),"""")"),"") | H50: =IFERROR(__xludf.DUMMYFUNCTION("IFERROR(INDEX(FILTER(Registrations!$E$2:$E100,Registrations!$H$2:$H100=$C50,Registrations!$L$2:$L100<>""Hủy"",Registrations!$L$2:$L100<>""Từ chối""),1),"""")"),"") | I50: =IFERROR(__xludf.DUMMYFUNCTION("IF(F50=0,"""",IF(IFERROR(INDEX(FILTER(Registrations!$F$2:$F100,Registrations!$H$2:$H100=$C50,Registrations!$L$2:$L100<>""Hủy"",Registrations!$L$2:$L100<>""Từ chối""),1),"""")=$A50,""Khớp"",""Sai kho""))"),"") | J50: GoodSet | K50: 15395000
A51: AYA | B51: 50 | C51: #050 | D51: 75NANO80ASA.ATV | E51: =IF(F51=0,"Còn trống",IF(F51=1,"Đã đăng ký","Trùng đăng ký")) -> Còn trống | F51: =COUNTIFS(Registrations!$H$2:$H100,$C51,Registrations!$L$2:$L100,"<>Hủy",Registrations!$L$2:$L100,"<>Từ chối") -> 0 | G51: =IFERROR(__xludf.DUMMYFUNCTION("IFERROR(INDEX(FILTER(Registrations!$D$2:$D100,Registrations!$H$2:$H100=$C51,Registrations!$L$2:$L100<>""Hủy"",Registrations!$L$2:$L100<>""Từ chối""),1),"""")"),"") | H51: =IFERROR(__xludf.DUMMYFUNCTION("IFERROR(INDEX(FILTER(Registrations!$E$2:$E100,Registrations!$H$2:$H100=$C51,Registrations!$L$2:$L100<>""Hủy"",Registrations!$L$2:$L100<>""Từ chối""),1),"""")"),"") | I51: =IFERROR(__xludf.DUMMYFUNCTION("IF(F51=0,"""",IF(IFERROR(INDEX(FILTER(Registrations!$F$2:$F100,Registrations!$H$2:$H100=$C51,Registrations!$L$2:$L100<>""Hủy"",Registrations!$L$2:$L100<>""Từ chối""),1),"""")=$A51,""Khớp"",""Sai kho""))"),"") | J51: GoodSet | K51: 15395000
A52: AYA | B52: 51 | C52: #051 | D52: 75NANO80ASA.ATV | E52: =IF(F52=0,"Còn trống",IF(F52=1,"Đã đăng ký","Trùng đăng ký")) -> Còn trống | F52: =COUNTIFS(Registrations!$H$2:$H100,$C52,Registrations!$L$2:$L100,"<>Hủy",Registrations!$L$2:$L100,"<>Từ chối") -> 0 | G52: =IFERROR(__xludf.DUMMYFUNCTION("IFERROR(INDEX(FILTER(Registrations!$D$2:$D100,Registrations!$H$2:$H100=$C52,Registrations!$L$2:$L100<>""Hủy"",Registrations!$L$2:$L100<>""Từ chối""),1),"""")"),"") | H52: =IFERROR(__xludf.DUMMYFUNCTION("IFERROR(INDEX(FILTER(Registrations!$E$2:$E100,Registrations!$H$2:$H100=$C52,Registrations!$L$2:$L100<>""Hủy"",Registrations!$L$2:$L100<>""Từ chối""),1),"""")"),"") | I52: =IFERROR(__xludf.DUMMYFUNCTION("IF(F52=0,"""",IF(IFERROR(INDEX(FILTER(Registrations!$F$2:$F100,Registrations!$H$2:$H100=$C52,Registrations!$L$2:$L100<>""Hủy"",Registrations!$L$2:$L100<>""Từ chối""),1),"""")=$A52,""Khớp"",""Sai kho""))"),"") | J52: GoodSet | K52: 15395000
A53: AYA | B53: 52 | C53: #052 | D53: 75NANO80ASA.ATV | E53: =IF(F53=0,"Còn trống",IF(F53=1,"Đã đăng ký","Trùng đăng ký")) -> Còn trống | F53: =COUNTIFS(Registrations!$H$2:$H100,$C53,Registrations!$L$2:$L100,"<>Hủy",Registrations!$L$2:$L100,"<>Từ chối") -> 0 | G53: =IFERROR(__xludf.DUMMYFUNCTION("IFERROR(INDEX(FILTER(Registrations!$D$2:$D100,Registrations!$H$2:$H100=$C53,Registrations!$L$2:$L100<>""Hủy"",Registrations!$L$2:$L100<>""Từ chối""),1),"""")"),"") | H53: =IFERROR(__xludf.DUMMYFUNCTION("IFERROR(INDEX(FILTER(Registrations!$E$2:$E100,Registrations!$H$2:$H100=$C53,Registrations!$L$2:$L100<>""Hủy"",Registrations!$L$2:$L100<>""Từ chối""),1),"""")"),"") | I53: =IFERROR(__xludf.DUMMYFUNCTION("IF(F53=0,"""",IF(IFERROR(INDEX(FILTER(Registrations!$F$2:$F100,Registrations!$H$2:$H100=$C53,Registrations!$L$2:$L100<>""Hủy"",Registrations!$L$2:$L100<>""Từ chối""),1),"""")=$A53,""Khớp"",""Sai kho""))"),"") | J53: GoodSet | K53: 15395000
A54: AYA | B54: 53 | C54: #053 | D54: 75NANO80ASA.ATV | E54: =IF(F54=0,"Còn trống",IF(F54=1,"Đã đăng ký","Trùng đăng ký")) -> Còn trống | F54: =COUNTIFS(Registrations!$H$2:$H100,$C54,Registrations!$L$2:$L100,"<>Hủy",Registrations!$L$2:$L100,"<>Từ chối") -> 0 | G54: =IFERROR(__xludf.DUMMYFUNCTION("IFERROR(INDEX(FILTER(Registrations!$D$2:$D100,Registrations!$H$2:$H100=$C54,Registrations!$L$2:$L100<>""Hủy"",Registrations!$L$2:$L100<>""Từ chối""),1),"""")"),"") | H54: =IFERROR(__xludf.DUMMYFUNCTION("IFERROR(INDEX(FILTER(Registrations!$E$2:$E100,Registrations!$H$2:$H100=$C54,Registrations!$L$2:$L100<>""Hủy"",Registrations!$L$2:$L100<>""Từ chối""),1),"""")"),"") | I54: =IFERROR(__xludf.DUMMYFUNCTION("IF(F54=0,"""",IF(IFERROR(INDEX(FILTER(Registrations!$F$2:$F100,Registrations!$H$2:$H100=$C54,Registrations!$L$2:$L100<>""Hủy"",Registrations!$L$2:$L100<>""Từ chối""),1),"""")=$A54,""Khớp"",""Sai kho""))"),"") | J54: GoodSet | K54: 15395000
A55: AYA | B55: 54 | C55: #054 | D55: 75NANO80ASA.ATV | E55: =IF(F55=0,"Còn trống",IF(F55=1,"Đã đăng ký","Trùng đăng ký")) -> Còn trống | F55: =COUNTIFS(Registrations!$H$2:$H100,$C55,Registrations!$L$2:$L100,"<>Hủy",Registrations!$L$2:$L100,"<>Từ chối") -> 0 | G55: =IFERROR(__xludf.DUMMYFUNCTION("IFERROR(INDEX(FILTER(Registrations!$D$2:$D100,Registrations!$H$2:$H100=$C55,Registrations!$L$2:$L100<>""Hủy"",Registrations!$L$2:$L100<>""Từ chối""),1),"""")"),"") | H55: =IFERROR(__xludf.DUMMYFUNCTION("IFERROR(INDEX(FILTER(Registrations!$E$2:$E100,Registrations!$H$2:$H100=$C55,Registrations!$L$2:$L100<>""Hủy"",Registrations!$L$2:$L100<>""Từ chối""),1),"""")"),"") | I55: =IFERROR(__xludf.DUMMYFUNCTION("IF(F55=0,"""",IF(IFERROR(INDEX(FILTER(Registrations!$F$2:$F100,Registrations!$H$2:$H100=$C55,Registrations!$L$2:$L100<>""Hủy"",Registrations!$L$2:$L100<>""Từ chối""),1),"""")=$A55,""Khớp"",""Sai kho""))"),"") | J55: GoodSet | K55: 15395000
A56: AYA | B56: 55 | C56: #055 | D56: 75NANO80ASA.ATV | E56: =IF(F56=0,"Còn trống",IF(F56=1,"Đã đăng ký","Trùng đăng ký")) -> Còn trống | F56: =COUNTIFS(Registrations!$H$2:$H100,$C56,Registrations!$L$2:$L100,"<>Hủy",Registrations!$L$2:$L100,"<>Từ chối") -> 0 | G56: =IFERROR(__xludf.DUMMYFUNCTION("IFERROR(INDEX(FILTER(Registrations!$D$2:$D100,Registrations!$H$2:$H100=$C56,Registrations!$L$2:$L100<>""Hủy"",Registrations!$L$2:$L100<>""Từ chối""),1),"""")"),"") | H56: =IFERROR(__xludf.DUMMYFUNCTION("IFERROR(INDEX(FILTER(Registrations!$E$2:$E100,Registrations!$H$2:$H100=$C56,Registrations!$L$2:$L100<>""Hủy"",Registrations!$L$2:$L100<>""Từ chối""),1),"""")"),"") | I56: =IFERROR(__xludf.DUMMYFUNCTION("IF(F56=0,"""",IF(IFERROR(INDEX(FILTER(Registrations!$F$2:$F100,Registrations!$H$2:$H100=$C56,Registrations!$L$2:$L100<>""Hủy"",Registrations!$L$2:$L100<>""Từ chối""),1),"""")=$A56,""Khớp"",""Sai kho""))"),"") | J56: GoodSet | K56: 15395000
A57: AYA | B57: 56 | C57: #056 | D57: 55NANO80ASA.ATV | E57: =IF(F57=0,"Còn trống",IF(F57=1,"Đã đăng ký","Trùng đăng ký")) -> Còn trống | F57: =COUNTIFS(Registrations!$H$2:$H100,$C57,Registrations!$L$2:$L100,"<>Hủy",Registrations!$L$2:$L100,"<>Từ chối") -> 0 | G57: =IFERROR(__xludf.DUMMYFUNCTION("IFERROR(INDEX(FILTER(Registrations!$D$2:$D100,Registrations!$H$2:$H100=$C57,Registrations!$L$2:$L100<>""Hủy"",Registrations!$L$2:$L100<>""Từ chối""),1),"""")"),"") | H57: =IFERROR(__xludf.DUMMYFUNCTION("IFERROR(INDEX(FILTER(Registrations!$E$2:$E100,Registrations!$H$2:$H100=$C57,Registrations!$L$2:$L100<>""Hủy"",Registrations!$L$2:$L100<>""Từ chối""),1),"""")"),"") | I57: =IFERROR(__xludf.DUMMYFUNCTION("IF(F57=0,"""",IF(IFERROR(INDEX(FILTER(Registrations!$F$2:$F100,Registrations!$H$2:$H100=$C57,Registrations!$L$2:$L100<>""Hủy"",Registrations!$L$2:$L100<>""Từ chối""),1),"""")=$A57,""Khớp"",""Sai kho""))"),"") | J57: GoodSet | K57: 8745000
A58: AYA | B58: 57 | C58: #057 | D58: 55NANO80ASA.ATV | E58: =IF(F58=0,"Còn trống",IF(F58=1,"Đã đăng ký","Trùng đăng ký")) -> Còn trống | F58: =COUNTIFS(Registrations!$H$2:$H100,$C58,Registrations!$L$2:$L100,"<>Hủy",Registrations!$L$2:$L100,"<>Từ chối") -> 0 | G58: =IFERROR(__xludf.DUMMYFUNCTION("IFERROR(INDEX(FILTER(Registrations!$D$2:$D100,Registrations!$H$2:$H100=$C58,Registrations!$L$2:$L100<>""Hủy"",Registrations!$L$2:$L100<>""Từ chối""),1),"""")"),"") | H58: =IFERROR(__xludf.DUMMYFUNCTION("IFERROR(INDEX(FILTER(Registrations!$E$2:$E100,Registrations!$H$2:$H100=$C58,Registrations!$L$2:$L100<>""Hủy"",Registrations!$L$2:$L100<>""Từ chối""),1),"""")"),"") | I58: =IFERROR(__xludf.DUMMYFUNCTION("IF(F58=0,"""",IF(IFERROR(INDEX(FILTER(Registrations!$F$2:$F100,Registrations!$H$2:$H100=$C58,Registrations!$L$2:$L100<>""Hủy"",Registrations!$L$2:$L100<>""Từ chối""),1),"""")=$A58,""Khớp"",""Sai kho""))"),"") | J58: GoodSet | K58: 8745000
A59: AYA | B59: 58 | C59: #058 | D59: 55NANO80ASA.ATV | E59: =IF(F59=0,"Còn trống",IF(F59=1,"Đã đăng ký","Trùng đăng ký")) -> Còn trống | F59: =COUNTIFS(Registrations!$H$2:$H100,$C59,Registrations!$L$2:$L100,"<>Hủy",Registrations!$L$2:$L100,"<>Từ chối") -> 0 | G59: =IFERROR(__xludf.DUMMYFUNCTION("IFERROR(INDEX(FILTER(Registrations!$D$2:$D100,Registrations!$H$2:$H100=$C59,Registrations!$L$2:$L100<>""Hủy"",Registrations!$L$2:$L100<>""Từ chối""),1),"""")"),"") | H59: =IFERROR(__xludf.DUMMYFUNCTION("IFERROR(INDEX(FILTER(Registrations!$E$2:$E100,Registrations!$H$2:$H100=$C59,Registrations!$L$2:$L100<>""Hủy"",Registrations!$L$2:$L100<>""Từ chối""),1),"""")"),"") | I59: =IFERROR(__xludf.DUMMYFUNCTION("IF(F59=0,"""",IF(IFERROR(INDEX(FILTER(Registrations!$F$2:$F100,Registrations!$H$2:$H100=$C59,Registrations!$L$2:$L100<>""Hủy"",Registrations!$L$2:$L100<>""Từ chối""),1),"""")=$A59,""Khớp"",""Sai kho""))"),"") | J59: GoodSet | K59: 8745000
A60: AYA | B60: 59 | C60: #059 | D60: 55NANO80ASA.ATV | E60: =IF(F60=0,"Còn trống",IF(F60=1,"Đã đăng ký","Trùng đăng ký")) -> Còn trống | F60: =COUNTIFS(Registrations!$H$2:$H100,$C60,Registrations!$L$2:$L100,"<>Hủy",Registrations!$L$2:$L100,"<>Từ chối") -> 0 | G60: =IFERROR(__xludf.DUMMYFUNCTION("IFERROR(INDEX(FILTER(Registrations!$D$2:$D100,Registrations!$H$2:$H100=$C60,Registrations!$L$2:$L100<>""Hủy"",Registrations!$L$2:$L100<>""Từ chối""),1),"""")"),"") | H60: =IFERROR(__xludf.DUMMYFUNCTION("IFERROR(INDEX(FILTER(Registrations!$E$2:$E100,Registrations!$H$2:$H100=$C60,Registrations!$L$2:$L100<>""Hủy"",Registrations!$L$2:$L100<>""Từ chối""),1),"""")"),"") | I60: =IFERROR(__xludf.DUMMYFUNCTION("IF(F60=0,"""",IF(IFERROR(INDEX(FILTER(Registrations!$F$2:$F100,Registrations!$H$2:$H100=$C60,Registrations!$L$2:$L100<>""Hủy"",Registrations!$L$2:$L100<>""Từ chối""),1),"""")=$A60,""Khớp"",""Sai kho""))"),"") | J60: GoodSet | K60: 8745000
A61: AYA | B61: 60 | C61: #060 | D61: 55NANO80ASA.ATV | E61: =IF(F61=0,"Còn trống",IF(F61=1,"Đã đăng ký","Trùng đăng ký")) -> Còn trống | F61: =COUNTIFS(Registrations!$H$2:$H100,$C61,Registrations!$L$2:$L100,"<>Hủy",Registrations!$L$2:$L100,"<>Từ chối") -> 0 | G61: =IFERROR(__xludf.DUMMYFUNCTION("IFERROR(INDEX(FILTER(Registrations!$D$2:$D100,Registrations!$H$2:$H100=$C61,Registrations!$L$2:$L100<>""Hủy"",Registrations!$L$2:$L100<>""Từ chối""),1),"""")"),"") | H61: =IFERROR(__xludf.DUMMYFUNCTION("IFERROR(INDEX(FILTER(Registrations!$E$2:$E100,Registrations!$H$2:$H100=$C61,Registrations!$L$2:$L100<>""Hủy"",Registrations!$L$2:$L100<>""Từ chối""),1),"""")"),"") | I61: =IFERROR(__xludf.DUMMYFUNCTION("IF(F61=0,"""",IF(IFERROR(INDEX(FILTER(Registrations!$F$2:$F100,Registrations!$H$2:$H100=$C61,Registrations!$L$2:$L100<>""Hủy"",Registrations!$L$2:$L100<>""Từ chối""),1),"""")=$A61,""Khớp"",""Sai kho""))"),"") | J61: GoodSet | K61: 8745000
A62: AYA | B62: 61 | C62: #061 | D62: 55NANO80ASA.ATV | E62: =IF(F62=0,"Còn trống",IF(F62=1,"Đã đăng ký","Trùng đăng ký")) -> Còn trống | F62: =COUNTIFS(Registrations!$H$2:$H100,$C62,Registrations!$L$2:$L100,"<>Hủy",Registrations!$L$2:$L100,"<>Từ chối") -> 0 | G62: =IFERROR(__xludf.DUMMYFUNCTION("IFERROR(INDEX(FILTER(Registrations!$D$2:$D100,Registrations!$H$2:$H100=$C62,Registrations!$L$2:$L100<>""Hủy"",Registrations!$L$2:$L100<>""Từ chối""),1),"""")"),"") | H62: =IFERROR(__xludf.DUMMYFUNCTION("IFERROR(INDEX(FILTER(Registrations!$E$2:$E100,Registrations!$H$2:$H100=$C62,Registrations!$L$2:$L100<>""Hủy"",Registrations!$L$2:$L100<>""Từ chối""),1),"""")"),"") | I62: =IFERROR(__xludf.DUMMYFUNCTION("IF(F62=0,"""",IF(IFERROR(INDEX(FILTER(Registrations!$F$2:$F100,Registrations!$H$2:$H100=$C62,Registrations!$L$2:$L100<>""Hủy"",Registrations!$L$2:$L100<>""Từ chối""),1),"""")=$A62,""Khớp"",""Sai kho""))"),"") | J62: GoodSet | K62: 8745000
A63: AYA | B63: 62 | C63: #062 | D63: 55NANO80ASA.ATV | E63: =IF(F63=0,"Còn trống",IF(F63=1,"Đã đăng ký","Trùng đăng ký")) -> Còn trống | F63: =COUNTIFS(Registrations!$H$2:$H100,$C63,Registrations!$L$2:$L100,"<>Hủy",Registrations!$L$2:$L100,"<>Từ chối") -> 0 | G63: =IFERROR(__xludf.DUMMYFUNCTION("IFERROR(INDEX(FILTER(Registrations!$D$2:$D100,Registrations!$H$2:$H100=$C63,Registrations!$L$2:$L100<>""Hủy"",Registrations!$L$2:$L100<>""Từ chối""),1),"""")"),"") | H63: =IFERROR(__xludf.DUMMYFUNCTION("IFERROR(INDEX(FILTER(Registrations!$E$2:$E100,Registrations!$H$2:$H100=$C63,Registrations!$L$2:$L100<>""Hủy"",Registrations!$L$2:$L100<>""Từ chối""),1),"""")"),"") | I63: =IFERROR(__xludf.DUMMYFUNCTION("IF(F63=0,"""",IF(IFERROR(INDEX(FILTER(Registrations!$F$2:$F100,Registrations!$H$2:$H100=$C63,Registrations!$L$2:$L100<>""Hủy"",Registrations!$L$2:$L100<>""Từ chối""),1),"""")=$A63,""Khớp"",""Sai kho""))"),"") | J63: GoodSet | K63: 8745000
A64: AYA | B64: 63 | C64: #063 | D64: 65UA7350PSB.ATVQ | E64: =IF(F64=0,"Còn trống",IF(F64=1,"Đã đăng ký","Trùng đăng ký")) -> Còn trống | F64: =COUNTIFS(Registrations!$H$2:$H100,$C64,Registrations!$L$2:$L100,"<>Hủy",Registrations!$L$2:$L100,"<>Từ chối") -> 0 | G64: =IFERROR(__xludf.DUMMYFUNCTION("IFERROR(INDEX(FILTER(Registrations!$D$2:$D100,Registrations!$H$2:$H100=$C64,Registrations!$L$2:$L100<>""Hủy"",Registrations!$L$2:$L100<>""Từ chối""),1),"""")"),"") | H64: =IFERROR(__xludf.DUMMYFUNCTION("IFERROR(INDEX(FILTER(Registrations!$E$2:$E100,Registrations!$H$2:$H100=$C64,Registrations!$L$2:$L100<>""Hủy"",Registrations!$L$2:$L100<>""Từ chối""),1),"""")"),"") | I64: =IFERROR(__xludf.DUMMYFUNCTION("IF(F64=0,"""",IF(IFERROR(INDEX(FILTER(Registrations!$F$2:$F100,Registrations!$H$2:$H100=$C64,Registrations!$L$2:$L100<>""Hủy"",Registrations!$L$2:$L100<>""Từ chối""),1),"""")=$A64,""Khớp"",""Sai kho""))"),"") | J64: GoodSet | K64: 9245000
A65: AYA | B65: 64 | C65: #064 | D65: 65UA7350PSB.ATVQ | E65: =IF(F65=0,"Còn trống",IF(F65=1,"Đã đăng ký","Trùng đăng ký")) -> Còn trống | F65: =COUNTIFS(Registrations!$H$2:$H100,$C65,Registrations!$L$2:$L100,"<>Hủy",Registrations!$L$2:$L100,"<>Từ chối") -> 0 | G65: =IFERROR(__xludf.DUMMYFUNCTION("IFERROR(INDEX(FILTER(Registrations!$D$2:$D100,Registrations!$H$2:$H100=$C65,Registrations!$L$2:$L100<>""Hủy"",Registrations!$L$2:$L100<>""Từ chối""),1),"""")"),"") | H65: =IFERROR(__xludf.DUMMYFUNCTION("IFERROR(INDEX(FILTER(Registrations!$E$2:$E100,Registrations!$H$2:$H100=$C65,Registrations!$L$2:$L100<>""Hủy"",Registrations!$L$2:$L100<>""Từ chối""),1),"""")"),"") | I65: =IFERROR(__xludf.DUMMYFUNCTION("IF(F65=0,"""",IF(IFERROR(INDEX(FILTER(Registrations!$F$2:$F100,Registrations!$H$2:$H100=$C65,Registrations!$L$2:$L100<>""Hủy"",Registrations!$L$2:$L100<>""Từ chối""),1),"""")=$A65,""Khớp"",""Sai kho""))"),"") | J65: GoodSet | K65: 9245000
A66: AYA | B66: 65 | C66: #065 | D66: 50UA7350PSB.ATVQ | E66: =IF(F66=0,"Còn trống",IF(F66=1,"Đã đăng ký","Trùng đăng ký")) -> Còn trống | F66: =COUNTIFS(Registrations!$H$2:$H100,$C66,Registrations!$L$2:$L100,"<>Hủy",Registrations!$L$2:$L100,"<>Từ chối") -> 0 | G66: =IFERROR(__xludf.DUMMYFUNCTION("IFERROR(INDEX(FILTER(Registrations!$D$2:$D100,Registrations!$H$2:$H100=$C66,Registrations!$L$2:$L100<>""Hủy"",Registrations!$L$2:$L100<>""Từ chối""),1),"""")"),"") | H66: =IFERROR(__xludf.DUMMYFUNCTION("IFERROR(INDEX(FILTER(Registrations!$E$2:$E100,Registrations!$H$2:$H100=$C66,Registrations!$L$2:$L100<>""Hủy"",Registrations!$L$2:$L100<>""Từ chối""),1),"""")"),"") | I66: =IFERROR(__xludf.DUMMYFUNCTION("IF(F66=0,"""",IF(IFERROR(INDEX(FILTER(Registrations!$F$2:$F100,Registrations!$H$2:$H100=$C66,Registrations!$L$2:$L100<>""Hủy"",Registrations!$L$2:$L100<>""Từ chối""),1),"""")=$A66,""Khớp"",""Sai kho""))"),"") | J66: GoodSet | K66: 6295000
A67: AYA | B67: 66 | C67: #066 | D67: 50UA7350PSB.ATVQ | E67: =IF(F67=0,"Còn trống",IF(F67=1,"Đã đăng ký","Trùng đăng ký")) -> Còn trống | F67: =COUNTIFS(Registrations!$H$2:$H100,$C67,Registrations!$L$2:$L100,"<>Hủy",Registrations!$L$2:$L100,"<>Từ chối") -> 0 | G67: =IFERROR(__xludf.DUMMYFUNCTION("IFERROR(INDEX(FILTER(Registrations!$D$2:$D100,Registrations!$H$2:$H100=$C67,Registrations!$L$2:$L100<>""Hủy"",Registrations!$L$2:$L100<>""Từ chối""),1),"""")"),"") | H67: =IFERROR(__xludf.DUMMYFUNCTION("IFERROR(INDEX(FILTER(Registrations!$E$2:$E100,Registrations!$H$2:$H100=$C67,Registrations!$L$2:$L100<>""Hủy"",Registrations!$L$2:$L100<>""Từ chối""),1),"""")"),"") | I67: =IFERROR(__xludf.DUMMYFUNCTION("IF(F67=0,"""",IF(IFERROR(INDEX(FILTER(Registrations!$F$2:$F100,Registrations!$H$2:$H100=$C67,Registrations!$L$2:$L100<>""Hủy"",Registrations!$L$2:$L100<>""Từ chối""),1),"""")=$A67,""Khớp"",""Sai kho""))"),"") | J67: GoodSet | K67: 6295000
A68: AYA | B68: 67 | C68: #067 | D68: 43UA7350PSB.ATVQ | E68: =IF(F68=0,"Còn trống",IF(F68=1,"Đã đăng ký","Trùng đăng ký")) -> Còn trống | F68: =COUNTIFS(Registrations!$H$2:$H100,$C68,Registrations!$L$2:$L100,"<>Hủy",Registrations!$L$2:$L100,"<>Từ chối") -> 0 | G68: =IFERROR(__xludf.DUMMYFUNCTION("IFERROR(INDEX(FILTER(Registrations!$D$2:$D100,Registrations!$H$2:$H100=$C68,Registrations!$L$2:$L100<>""Hủy"",Registrations!$L$2:$L100<>""Từ chối""),1),"""")"),"") | H68: =IFERROR(__xludf.DUMMYFUNCTION("IFERROR(INDEX(FILTER(Registrations!$E$2:$E100,Registrations!$H$2:$H100=$C68,Registrations!$L$2:$L100<>""Hủy"",Registrations!$L$2:$L100<>""Từ chối""),1),"""")"),"") | I68: =IFERROR(__xludf.DUMMYFUNCTION("IF(F68=0,"""",IF(IFERROR(INDEX(FILTER(Registrations!$F$2:$F100,Registrations!$H$2:$H100=$C68,Registrations!$L$2:$L100<>""Hủy"",Registrations!$L$2:$L100<>""Từ chối""),1),"""")=$A68,""Khớp"",""Sai kho""))"),"") | J68: GoodSet | K68: 4845000
A69: AYA | B69: 68 | C69: #068 | D69: 43UA7350PSB.ATVQ | E69: =IF(F69=0,"Còn trống",IF(F69=1,"Đã đăng ký","Trùng đăng ký")) -> Còn trống | F69: =COUNTIFS(Registrations!$H$2:$H100,$C69,Registrations!$L$2:$L100,"<>Hủy",Registrations!$L$2:$L100,"<>Từ chối") -> 0 | G69: =IFERROR(__xludf.DUMMYFUNCTION("IFERROR(INDEX(FILTER(Registrations!$D$2:$D100,Registrations!$H$2:$H100=$C69,Registrations!$L$2:$L100<>""Hủy"",Registrations!$L$2:$L100<>""Từ chối""),1),"""")"),"") | H69: =IFERROR(__xludf.DUMMYFUNCTION("IFERROR(INDEX(FILTER(Registrations!$E$2:$E100,Registrations!$H$2:$H100=$C69,Registrations!$L$2:$L100<>""Hủy"",Registrations!$L$2:$L100<>""Từ chối""),1),"""")"),"") | I69: =IFERROR(__xludf.DUMMYFUNCTION("IF(F69=0,"""",IF(IFERROR(INDEX(FILTER(Registrations!$F$2:$F100,Registrations!$H$2:$H100=$C69,Registrations!$L$2:$L100<>""Hủy"",Registrations!$L$2:$L100<>""Từ chối""),1),"""")=$A69,""Khớp"",""Sai kho""))"),"") | J69: GoodSet | K69: 4845000
A70: AYC | B70: 69 | C70: #069 | D70: 75QNED80ASA.ATV | E70: =IF(F70=0,"Còn trống",IF(F70=1,"Đã đăng ký","Trùng đăng ký")) -> Còn trống | F70: =COUNTIFS(Registrations!$H$2:$H100,$C70,Registrations!$L$2:$L100,"<>Hủy",Registrations!$L$2:$L100,"<>Từ chối") -> 0 | G70: =IFERROR(__xludf.DUMMYFUNCTION("IFERROR(INDEX(FILTER(Registrations!$D$2:$D100,Registrations!$H$2:$H100=$C70,Registrations!$L$2:$L100<>""Hủy"",Registrations!$L$2:$L100<>""Từ chối""),1),"""")"),"") | H70: =IFERROR(__xludf.DUMMYFUNCTION("IFERROR(INDEX(FILTER(Registrations!$E$2:$E100,Registrations!$H$2:$H100=$C70,Registrations!$L$2:$L100<>""Hủy"",Registrations!$L$2:$L100<>""Từ chối""),1),"""")"),"") | I70: =IFERROR(__xludf.DUMMYFUNCTION("IF(F70=0,"""",IF(IFERROR(INDEX(FILTER(Registrations!$F$2:$F100,Registrations!$H$2:$H100=$C70,Registrations!$L$2:$L100<>""Hủy"",Registrations!$L$2:$L100<>""Từ chối""),1),"""")=$A70,""Khớp"",""Sai kho""))"),"") | J70: GoodSet | K70: 17095000
A71: AYC | B71: 70 | C71: #070 | D71: 75QNED80ASA.ATV | E71: =IF(F71=0,"Còn trống",IF(F71=1,"Đã đăng ký","Trùng đăng ký")) -> Còn trống | F71: =COUNTIFS(Registrations!$H$2:$H100,$C71,Registrations!$L$2:$L100,"<>Hủy",Registrations!$L$2:$L100,"<>Từ chối") -> 0 | G71: =IFERROR(__xludf.DUMMYFUNCTION("IFERROR(INDEX(FILTER(Registrations!$D$2:$D100,Registrations!$H$2:$H100=$C71,Registrations!$L$2:$L100<>""Hủy"",Registrations!$L$2:$L100<>""Từ chối""),1),"""")"),"") | H71: =IFERROR(__xludf.DUMMYFUNCTION("IFERROR(INDEX(FILTER(Registrations!$E$2:$E100,Registrations!$H$2:$H100=$C71,Registrations!$L$2:$L100<>""Hủy"",Registrations!$L$2:$L100<>""Từ chối""),1),"""")"),"") | I71: =IFERROR(__xludf.DUMMYFUNCTION("IF(F71=0,"""",IF(IFERROR(INDEX(FILTER(Registrations!$F$2:$F100,Registrations!$H$2:$H100=$C71,Registrations!$L$2:$L100<>""Hủy"",Registrations!$L$2:$L100<>""Từ chối""),1),"""")=$A71,""Khớp"",""Sai kho""))"),"") | J71: GoodSet | K71: 17095000
A72: AYC | B72: 71 | C72: #071 | D72: 75NANO80ASA.ATV | E72: =IF(F72=0,"Còn trống",IF(F72=1,"Đã đăng ký","Trùng đăng ký")) -> Còn trống | F72: =COUNTIFS(Registrations!$H$2:$H100,$C72,Registrations!$L$2:$L100,"<>Hủy",Registrations!$L$2:$L100,"<>Từ chối") -> 0 | G72: =IFERROR(__xludf.DUMMYFUNCTION("IFERROR(INDEX(FILTER(Registrations!$D$2:$D100,Registrations!$H$2:$H100=$C72,Registrations!$L$2:$L100<>""Hủy"",Registrations!$L$2:$L100<>""Từ chối""),1),"""")"),"") | H72: =IFERROR(__xludf.DUMMYFUNCTION("IFERROR(INDEX(FILTER(Registrations!$E$2:$E100,Registrations!$H$2:$H100=$C72,Registrations!$L$2:$L100<>""Hủy"",Registrations!$L$2:$L100<>""Từ chối""),1),"""")"),"") | I72: =IFERROR(__xludf.DUMMYFUNCTION("IF(F72=0,"""",IF(IFERROR(INDEX(FILTER(Registrations!$F$2:$F100,Registrations!$H$2:$H100=$C72,Registrations!$L$2:$L100<>""Hủy"",Registrations!$L$2:$L100<>""Từ chối""),1),"""")=$A72,""Khớp"",""Sai kho""))"),"") | J72: GoodSet | K72: 15395000
A73: AYC | B73: 72 | C73: #072 | D73: 75NANO80ASA.ATV | E73: =IF(F73=0,"Còn trống",IF(F73=1,"Đã đăng ký","Trùng đăng ký")) -> Còn trống | F73: =COUNTIFS(Registrations!$H$2:$H100,$C73,Registrations!$L$2:$L100,"<>Hủy",Registrations!$L$2:$L100,"<>Từ chối") -> 0 | G73: =IFERROR(__xludf.DUMMYFUNCTION("IFERROR(INDEX(FILTER(Registrations!$D$2:$D100,Registrations!$H$2:$H100=$C73,Registrations!$L$2:$L100<>""Hủy"",Registrations!$L$2:$L100<>""Từ chối""),1),"""")"),"") | H73: =IFERROR(__xludf.DUMMYFUNCTION("IFERROR(INDEX(FILTER(Registrations!$E$2:$E100,Registrations!$H$2:$H100=$C73,Registrations!$L$2:$L100<>""Hủy"",Registrations!$L$2:$L100<>""Từ chối""),1),"""")"),"") | I73: =IFERROR(__xludf.DUMMYFUNCTION("IF(F73=0,"""",IF(IFERROR(INDEX(FILTER(Registrations!$F$2:$F100,Registrations!$H$2:$H100=$C73,Registrations!$L$2:$L100<>""Hủy"",Registrations!$L$2:$L100<>""Từ chối""),1),"""")=$A73,""Khớp"",""Sai kho""))"),"") | J73: GoodSet | K73: 15395000
A74: AYC | B74: 73 | C74: #073 | D74: 75NANO80ASA.ATV | E74: =IF(F74=0,"Còn trống",IF(F74=1,"Đã đăng ký","Trùng đăng ký")) -> Còn trống | F74: =COUNTIFS(Registrations!$H$2:$H100,$C74,Registrations!$L$2:$L100,"<>Hủy",Registrations!$L$2:$L100,"<>Từ chối") -> 0 | G74: =IFERROR(__xludf.DUMMYFUNCTION("IFERROR(INDEX(FILTER(Registrations!$D$2:$D100,Registrations!$H$2:$H100=$C74,Registrations!$L$2:$L100<>""Hủy"",Registrations!$L$2:$L100<>""Từ chối""),1),"""")"),"") | H74: =IFERROR(__xludf.DUMMYFUNCTION("IFERROR(INDEX(FILTER(Registrations!$E$2:$E100,Registrations!$H$2:$H100=$C74,Registrations!$L$2:$L100<>""Hủy"",Registrations!$L$2:$L100<>""Từ chối""),1),"""")"),"") | I74: =IFERROR(__xludf.DUMMYFUNCTION("IF(F74=0,"""",IF(IFERROR(INDEX(FILTER(Registrations!$F$2:$F100,Registrations!$H$2:$H100=$C74,Registrations!$L$2:$L100<>""Hủy"",Registrations!$L$2:$L100<>""Từ chối""),1),"""")=$A74,""Khớp"",""Sai kho""))"),"") | J74: GoodSet | K74: 15395000
A75: AYC | B75: 74 | C75: #074 | D75: 75NANO80ASA.ATV | E75: =IF(F75=0,"Còn trống",IF(F75=1,"Đã đăng ký","Trùng đăng ký")) -> Còn trống | F75: =COUNTIFS(Registrations!$H$2:$H100,$C75,Registrations!$L$2:$L100,"<>Hủy",Registrations!$L$2:$L100,"<>Từ chối") -> 0 | G75: =IFERROR(__xludf.DUMMYFUNCTION("IFERROR(INDEX(FILTER(Registrations!$D$2:$D100,Registrations!$H$2:$H100=$C75,Registrations!$L$2:$L100<>""Hủy"",Registrations!$L$2:$L100<>""Từ chối""),1),"""")"),"") | H75: =IFERROR(__xludf.DUMMYFUNCTION("IFERROR(INDEX(FILTER(Registrations!$E$2:$E100,Registrations!$H$2:$H100=$C75,Registrations!$L$2:$L100<>""Hủy"",Registrations!$L$2:$L100<>""Từ chối""),1),"""")"),"") | I75: =IFERROR(__xludf.DUMMYFUNCTION("IF(F75=0,"""",IF(IFERROR(INDEX(FILTER(Registrations!$F$2:$F100,Registrations!$H$2:$H100=$C75,Registrations!$L$2:$L100<>""Hủy"",Registrations!$L$2:$L100<>""Từ chối""),1),"""")=$A75,""Khớp"",""Sai kho""))"),"") | J75: GoodSet | K75: 15395000
A76: AYC | B76: 75 | C76: #075 | D76: 75NANO80ASA.ATV | E76: =IF(F76=0,"Còn trống",IF(F76=1,"Đã đăng ký","Trùng đăng ký")) -> Còn trống | F76: =COUNTIFS(Registrations!$H$2:$H100,$C76,Registrations!$L$2:$L100,"<>Hủy",Registrations!$L$2:$L100,"<>Từ chối") -> 0 | G76: =IFERROR(__xludf.DUMMYFUNCTION("IFERROR(INDEX(FILTER(Registrations!$D$2:$D100,Registrations!$H$2:$H100=$C76,Registrations!$L$2:$L100<>""Hủy"",Registrations!$L$2:$L100<>""Từ chối""),1),"""")"),"") | H76: =IFERROR(__xludf.DUMMYFUNCTION("IFERROR(INDEX(FILTER(Registrations!$E$2:$E100,Registrations!$H$2:$H100=$C76,Registrations!$L$2:$L100<>""Hủy"",Registrations!$L$2:$L100<>""Từ chối""),1),"""")"),"") | I76: =IFERROR(__xludf.DUMMYFUNCTION("IF(F76=0,"""",IF(IFERROR(INDEX(FILTER(Registrations!$F$2:$F100,Registrations!$H$2:$H100=$C76,Registrations!$L$2:$L100<>""Hủy"",Registrations!$L$2:$L100<>""Từ chối""),1),"""")=$A76,""Khớp"",""Sai kho""))"),"") | J76: GoodSet | K76: 15395000
A77: AYC | B77: 76 | C77: #076 | D77: 75NANO80ASA.ATV | E77: =IF(F77=0,"Còn trống",IF(F77=1,"Đã đăng ký","Trùng đăng ký")) -> Còn trống | F77: =COUNTIFS(Registrations!$H$2:$H100,$C77,Registrations!$L$2:$L100,"<>Hủy",Registrations!$L$2:$L100,"<>Từ chối") -> 0 | G77: =IFERROR(__xludf.DUMMYFUNCTION("IFERROR(INDEX(FILTER(Registrations!$D$2:$D100,Registrations!$H$2:$H100=$C77,Registrations!$L$2:$L100<>""Hủy"",Registrations!$L$2:$L100<>""Từ chối""),1),"""")"),"") | H77: =IFERROR(__xludf.DUMMYFUNCTION("IFERROR(INDEX(FILTER(Registrations!$E$2:$E100,Registrations!$H$2:$H100=$C77,Registrations!$L$2:$L100<>""Hủy"",Registrations!$L$2:$L100<>""Từ chối""),1),"""")"),"") | I77: =IFERROR(__xludf.DUMMYFUNCTION("IF(F77=0,"""",IF(IFERROR(INDEX(FILTER(Registrations!$F$2:$F100,Registrations!$H$2:$H100=$C77,Registrations!$L$2:$L100<>""Hủy"",Registrations!$L$2:$L100<>""Từ chối""),1),"""")=$A77,""Khớp"",""Sai kho""))"),"") | J77: GoodSet | K77: 15395000
A78: AYC | B78: 77 | C78: #077 | D78: 75NANO80ASA.ATV | E78: =IF(F78=0,"Còn trống",IF(F78=1,"Đã đăng ký","Trùng đăng ký")) -> Còn trống | F78: =COUNTIFS(Registrations!$H$2:$H100,$C78,Registrations!$L$2:$L100,"<>Hủy",Registrations!$L$2:$L100,"<>Từ chối") -> 0 | G78: =IFERROR(__xludf.DUMMYFUNCTION("IFERROR(INDEX(FILTER(Registrations!$D$2:$D100,Registrations!$H$2:$H100=$C78,Registrations!$L$2:$L100<>""Hủy"",Registrations!$L$2:$L100<>""Từ chối""),1),"""")"),"") | H78: =IFERROR(__xludf.DUMMYFUNCTION("IFERROR(INDEX(FILTER(Registrations!$E$2:$E100,Registrations!$H$2:$H100=$C78,Registrations!$L$2:$L100<>""Hủy"",Registrations!$L$2:$L100<>""Từ chối""),1),"""")"),"") | I78: =IFERROR(__xludf.DUMMYFUNCTION("IF(F78=0,"""",IF(IFERROR(INDEX(FILTER(Registrations!$F$2:$F100,Registrations!$H$2:$H100=$C78,Registrations!$L$2:$L100<>""Hủy"",Registrations!$L$2:$L100<>""Từ chối""),1),"""")=$A78,""Khớp"",""Sai kho""))"),"") | J78: GoodSet | K78: 15395000
A79: AYC | B79: 78 | C79: #078 | D79: 75NANO80ASA.ATV | E79: =IF(F79=0,"Còn trống",IF(F79=1,"Đã đăng ký","Trùng đăng ký")) -> Còn trống | F79: =COUNTIFS(Registrations!$H$2:$H100,$C79,Registrations!$L$2:$L100,"<>Hủy",Registrations!$L$2:$L100,"<>Từ chối") -> 0 | G79: =IFERROR(__xludf.DUMMYFUNCTION("IFERROR(INDEX(FILTER(Registrations!$D$2:$D100,Registrations!$H$2:$H100=$C79,Registrations!$L$2:$L100<>""Hủy"",Registrations!$L$2:$L100<>""Từ chối""),1),"""")"),"") | H79: =IFERROR(__xludf.DUMMYFUNCTION("IFERROR(INDEX(FILTER(Registrations!$E$2:$E100,Registrations!$H$2:$H100=$C79,Registrations!$L$2:$L100<>""Hủy"",Registrations!$L$2:$L100<>""Từ chối""),1),"""")"),"") | I79: =IFERROR(__xludf.DUMMYFUNCTION("IF(F79=0,"""",IF(IFERROR(INDEX(FILTER(Registrations!$F$2:$F100,Registrations!$H$2:$H100=$C79,Registrations!$L$2:$L100<>""Hủy"",Registrations!$L$2:$L100<>""Từ chối""),1),"""")=$A79,""Khớp"",""Sai kho""))"),"") | J79: GoodSet | K79: 15395000
A80: AYC | B80: 79 | C80: #079 | D80: 75NANO80ASA.ATV | E80: =IF(F80=0,"Còn trống",IF(F80=1,"Đã đăng ký","Trùng đăng ký")) -> Còn trống | F80: =COUNTIFS(Registrations!$H$2:$H100,$C80,Registrations!$L$2:$L100,"<>Hủy",Registrations!$L$2:$L100,"<>Từ chối") -> 0 | G80: =IFERROR(__xludf.DUMMYFUNCTION("IFERROR(INDEX(FILTER(Registrations!$D$2:$D100,Registrations!$H$2:$H100=$C80,Registrations!$L$2:$L100<>""Hủy"",Registrations!$L$2:$L100<>""Từ chối""),1),"""")"),"") | H80: =IFERROR(__xludf.DUMMYFUNCTION("IFERROR(INDEX(FILTER(Registrations!$E$2:$E100,Registrations!$H$2:$H100=$C80,Registrations!$L$2:$L100<>""Hủy"",Registrations!$L$2:$L100<>""Từ chối""),1),"""")"),"") | I80: =IFERROR(__xludf.DUMMYFUNCTION("IF(F80=0,"""",IF(IFERROR(INDEX(FILTER(Registrations!$F$2:$F100,Registrations!$H$2:$H100=$C80,Registrations!$L$2:$L100<>""Hủy"",Registrations!$L$2:$L100<>""Từ chối""),1),"""")=$A80,""Khớp"",""Sai kho""))"),"") | J80: GoodSet | K80: 15395000
A81: AYC | B81: 80 | C81: #080 | D81: 75NANO80ASA.ATV | E81: =IF(F81=0,"Còn trống",IF(F81=1,"Đã đăng ký","Trùng đăng ký")) -> Còn trống | F81: =COUNTIFS(Registrations!$H$2:$H100,$C81,Registrations!$L$2:$L100,"<>Hủy",Registrations!$L$2:$L100,"<>Từ chối") -> 0 | G81: =IFERROR(__xludf.DUMMYFUNCTION("IFERROR(INDEX(FILTER(Registrations!$D$2:$D100,Registrations!$H$2:$H100=$C81,Registrations!$L$2:$L100<>""Hủy"",Registrations!$L$2:$L100<>""Từ chối""),1),"""")"),"") | H81: =IFERROR(__xludf.DUMMYFUNCTION("IFERROR(INDEX(FILTER(Registrations!$E$2:$E100,Registrations!$H$2:$H100=$C81,Registrations!$L$2:$L100<>""Hủy"",Registrations!$L$2:$L100<>""Từ chối""),1),"""")"),"") | I81: =IFERROR(__xludf.DUMMYFUNCTION("IF(F81=0,"""",IF(IFERROR(INDEX(FILTER(Registrations!$F$2:$F100,Registrations!$H$2:$H100=$C81,Registrations!$L$2:$L100<>""Hủy"",Registrations!$L$2:$L100<>""Từ chối""),1),"""")=$A81,""Khớp"",""Sai kho""))"),"") | J81: GoodSet | K81: 15395000
A82: AYC | B82: 81 | C82: #081 | D82: 75NANO80ASA.ATV | E82: =IF(F82=0,"Còn trống",IF(F82=1,"Đã đăng ký","Trùng đăng ký")) -> Còn trống | F82: =COUNTIFS(Registrations!$H$2:$H100,$C82,Registrations!$L$2:$L100,"<>Hủy",Registrations!$L$2:$L100,"<>Từ chối") -> 0 | G82: =IFERROR(__xludf.DUMMYFUNCTION("IFERROR(INDEX(FILTER(Registrations!$D$2:$D100,Registrations!$H$2:$H100=$C82,Registrations!$L$2:$L100<>""Hủy"",Registrations!$L$2:$L100<>""Từ chối""),1),"""")"),"") | H82: =IFERROR(__xludf.DUMMYFUNCTION("IFERROR(INDEX(FILTER(Registrations!$E$2:$E100,Registrations!$H$2:$H100=$C82,Registrations!$L$2:$L100<>""Hủy"",Registrations!$L$2:$L100<>""Từ chối""),1),"""")"),"") | I82: =IFERROR(__xludf.DUMMYFUNCTION("IF(F82=0,"""",IF(IFERROR(INDEX(FILTER(Registrations!$F$2:$F100,Registrations!$H$2:$H100=$C82,Registrations!$L$2:$L100<>""Hủy"",Registrations!$L$2:$L100<>""Từ chối""),1),"""")=$A82,""Khớp"",""Sai kho""))"),"") | J82: GoodSet | K82: 15395000
A83: AYB | B83: 82 | C83: #082 | D83: 50UA7350PSB.ATVQ | E83: =IF(F83=0,"Còn trống",IF(F83=1,"Đã đăng ký","Trùng đăng ký")) -> Còn trống | F83: =COUNTIFS(Registrations!$H$2:$H100,$C83,Registrations!$L$2:$L100,"<>Hủy",Registrations!$L$2:$L100,"<>Từ chối") -> 0 | G83: =IFERROR(__xludf.DUMMYFUNCTION("IFERROR(INDEX(FILTER(Registrations!$D$2:$D100,Registrations!$H$2:$H100=$C83,Registrations!$L$2:$L100<>""Hủy"",Registrations!$L$2:$L100<>""Từ chối""),1),"""")"),"") | H83: =IFERROR(__xludf.DUMMYFUNCTION("IFERROR(INDEX(FILTER(Registrations!$E$2:$E100,Registrations!$H$2:$H100=$C83,Registrations!$L$2:$L100<>""Hủy"",Registrations!$L$2:$L100<>""Từ chối""),1),"""")"),"") | I83: =IFERROR(__xludf.DUMMYFUNCTION("IF(F83=0,"""",IF(IFERROR(INDEX(FILTER(Registrations!$F$2:$F100,Registrations!$H$2:$H100=$C83,Registrations!$L$2:$L100<>""Hủy"",Registrations!$L$2:$L100<>""Từ chối""),1),"""")=$A83,""Khớp"",""Sai kho""))"),"") | J83: GoodSet | K83: 6295000
A84: AYC | B84: 83 | C84: #083 | D84: 65QNED70ASA.ATV | E84: =IF(F84=0,"Còn trống",IF(F84=1,"Đã đăng ký","Trùng đăng ký")) -> Còn trống | F84: =COUNTIFS(Registrations!$H$2:$H100,$C84,Registrations!$L$2:$L100,"<>Hủy",Registrations!$L$2:$L100,"<>Từ chối") -> 0 | G84: =IFERROR(__xludf.DUMMYFUNCTION("IFERROR(INDEX(FILTER(Registrations!$D$2:$D100,Registrations!$H$2:$H100=$C84,Registrations!$L$2:$L100<>""Hủy"",Registrations!$L$2:$L100<>""Từ chối""),1),"""")"),"") | H84: =IFERROR(__xludf.DUMMYFUNCTION("IFERROR(INDEX(FILTER(Registrations!$E$2:$E100,Registrations!$H$2:$H100=$C84,Registrations!$L$2:$L100<>""Hủy"",Registrations!$L$2:$L100<>""Từ chối""),1),"""")"),"") | I84: =IFERROR(__xludf.DUMMYFUNCTION("IF(F84=0,"""",IF(IFERROR(INDEX(FILTER(Registrations!$F$2:$F100,Registrations!$H$2:$H100=$C84,Registrations!$L$2:$L100<>""Hủy"",Registrations!$L$2:$L100<>""Từ chối""),1),"""")=$A84,""Khớp"",""Sai kho""))"),"") | J84: GoodSet | K84: 11450000
A85: AYC | B85: 84 | C85: #084 | D85: 65QNED70ASA.ATV | E85: =IF(F85=0,"Còn trống",IF(F85=1,"Đã đăng ký","Trùng đăng ký")) -> Còn trống | F85: =COUNTIFS(Registrations!$H$2:$H100,$C85,Registrations!$L$2:$L100,"<>Hủy",Registrations!$L$2:$L100,"<>Từ chối") -> 0 | G85: =IFERROR(__xludf.DUMMYFUNCTION("IFERROR(INDEX(FILTER(Registrations!$D$2:$D100,Registrations!$H$2:$H100=$C85,Registrations!$L$2:$L100<>""Hủy"",Registrations!$L$2:$L100<>""Từ chối""),1),"""")"),"") | H85: =IFERROR(__xludf.DUMMYFUNCTION("IFERROR(INDEX(FILTER(Registrations!$E$2:$E100,Registrations!$H$2:$H100=$C85,Registrations!$L$2:$L100<>""Hủy"",Registrations!$L$2:$L100<>""Từ chối""),1),"""")"),"") | I85: =IFERROR(__xludf.DUMMYFUNCTION("IF(F85=0,"""",IF(IFERROR(INDEX(FILTER(Registrations!$F$2:$F100,Registrations!$H$2:$H100=$C85,Registrations!$L$2:$L100<>""Hủy"",Registrations!$L$2:$L100<>""Từ chối""),1),"""")=$A85,""Khớp"",""Sai kho""))"),"") | J85: GoodSet | K85: 11450000
A86: AYC | B86: 85 | C86: #085 | D86: 65QNED70ASA.ATV | E86: =IF(F86=0,"Còn trống",IF(F86=1,"Đã đăng ký","Trùng đăng ký")) -> Còn trống | F86: =COUNTIFS(Registrations!$H$2:$H100,$C86,Registrations!$L$2:$L100,"<>Hủy",Registrations!$L$2:$L100,"<>Từ chối") -> 0 | G86: =IFERROR(__xludf.DUMMYFUNCTION("IFERROR(INDEX(FILTER(Registrations!$D$2:$D100,Registrations!$H$2:$H100=$C86,Registrations!$L$2:$L100<>""Hủy"",Registrations!$L$2:$L100<>""Từ chối""),1),"""")"),"") | H86: =IFERROR(__xludf.DUMMYFUNCTION("IFERROR(INDEX(FILTER(Registrations!$E$2:$E100,Registrations!$H$2:$H100=$C86,Registrations!$L$2:$L100<>""Hủy"",Registrations!$L$2:$L100<>""Từ chối""),1),"""")"),"") | I86: =IFERROR(__xludf.DUMMYFUNCTION("IF(F86=0,"""",IF(IFERROR(INDEX(FILTER(Registrations!$F$2:$F100,Registrations!$H$2:$H100=$C86,Registrations!$L$2:$L100<>""Hủy"",Registrations!$L$2:$L100<>""Từ chối""),1),"""")=$A86,""Khớp"",""Sai kho""))"),"") | J86: GoodSet | K86: 11450000
A87: AYC | B87: 86 | C87: #086 | D87: 65QNED70ASA.ATV | E87: =IF(F87=0,"Còn trống",IF(F87=1,"Đã đăng ký","Trùng đăng ký")) -> Còn trống | F87: =COUNTIFS(Registrations!$H$2:$H100,$C87,Registrations!$L$2:$L100,"<>Hủy",Registrations!$L$2:$L100,"<>Từ chối") -> 0 | G87: =IFERROR(__xludf.DUMMYFUNCTION("IFERROR(INDEX(FILTER(Registrations!$D$2:$D100,Registrations!$H$2:$H100=$C87,Registrations!$L$2:$L100<>""Hủy"",Registrations!$L$2:$L100<>""Từ chối""),1),"""")"),"") | H87: =IFERROR(__xludf.DUMMYFUNCTION("IFERROR(INDEX(FILTER(Registrations!$E$2:$E100,Registrations!$H$2:$H100=$C87,Registrations!$L$2:$L100<>""Hủy"",Registrations!$L$2:$L100<>""Từ chối""),1),"""")"),"") | I87: =IFERROR(__xludf.DUMMYFUNCTION("IF(F87=0,"""",IF(IFERROR(INDEX(FILTER(Registrations!$F$2:$F100,Registrations!$H$2:$H100=$C87,Registrations!$L$2:$L100<>""Hủy"",Registrations!$L$2:$L100<>""Từ chối""),1),"""")=$A87,""Khớp"",""Sai kho""))"),"") | J87: GoodSet | K87: 11450000
A88: AYC | B88: 87 | C88: #087 | D88: 43QNED70ASA.ATV | E88: =IF(F88=0,"Còn trống",IF(F88=1,"Đã đăng ký","Trùng đăng ký")) -> Còn trống | F88: =COUNTIFS(Registrations!$H$2:$H100,$C88,Registrations!$L$2:$L100,"<>Hủy",Registrations!$L$2:$L100,"<>Từ chối") -> 0 | G88: =IFERROR(__xludf.DUMMYFUNCTION("IFERROR(INDEX(FILTER(Registrations!$D$2:$D100,Registrations!$H$2:$H100=$C88,Registrations!$L$2:$L100<>""Hủy"",Registrations!$L$2:$L100<>""Từ chối""),1),"""")"),"") | H88: =IFERROR(__xludf.DUMMYFUNCTION("IFERROR(INDEX(FILTER(Registrations!$E$2:$E100,Registrations!$H$2:$H100=$C88,Registrations!$L$2:$L100<>""Hủy"",Registrations!$L$2:$L100<>""Từ chối""),1),"""")"),"") | I88: =IFERROR(__xludf.DUMMYFUNCTION("IF(F88=0,"""",IF(IFERROR(INDEX(FILTER(Registrations!$F$2:$F100,Registrations!$H$2:$H100=$C88,Registrations!$L$2:$L100<>""Hủy"",Registrations!$L$2:$L100<>""Từ chối""),1),"""")=$A88,""Khớp"",""Sai kho""))"),"") | J88: GoodSet | K88: 6545000
A89: AYC | B89: 88 | C89: #088 | D89: 43QNED70ASA.ATV | E89: =IF(F89=0,"Còn trống",IF(F89=1,"Đã đăng ký","Trùng đăng ký")) -> Còn trống | F89: =COUNTIFS(Registrations!$H$2:$H100,$C89,Registrations!$L$2:$L100,"<>Hủy",Registrations!$L$2:$L100,"<>Từ chối") -> 0 | G89: =IFERROR(__xludf.DUMMYFUNCTION("IFERROR(INDEX(FILTER(Registrations!$D$2:$D100,Registrations!$H$2:$H100=$C89,Registrations!$L$2:$L100<>""Hủy"",Registrations!$L$2:$L100<>""Từ chối""),1),"""")"),"") | H89: =IFERROR(__xludf.DUMMYFUNCTION("IFERROR(INDEX(FILTER(Registrations!$E$2:$E100,Registrations!$H$2:$H100=$C89,Registrations!$L$2:$L100<>""Hủy"",Registrations!$L$2:$L100<>""Từ chối""),1),"""")"),"") | I89: =IFERROR(__xludf.DUMMYFUNCTION("IF(F89=0,"""",IF(IFERROR(INDEX(FILTER(Registrations!$F$2:$F100,Registrations!$H$2:$H100=$C89,Registrations!$L$2:$L100<>""Hủy"",Registrations!$L$2:$L100<>""Từ chối""),1),"""")=$A89,""Khớp"",""Sai kho""))"),"") | J89: GoodSet | K89: 6545000
A90: AYC | B90: 89 | C90: #089 | D90: 65UA8450PSA.ATV | E90: =IF(F90=0,"Còn trống",IF(F90=1,"Đã đăng ký","Trùng đăng ký")) -> Còn trống | F90: =COUNTIFS(Registrations!$H$2:$H100,$C90,Registrations!$L$2:$L100,"<>Hủy",Registrations!$L$2:$L100,"<>Từ chối") -> 0 | G90: =IFERROR(__xludf.DUMMYFUNCTION("IFERROR(INDEX(FILTER(Registrations!$D$2:$D100,Registrations!$H$2:$H100=$C90,Registrations!$L$2:$L100<>""Hủy"",Registrations!$L$2:$L100<>""Từ chối""),1),"""")"),"") | H90: =IFERROR(__xludf.DUMMYFUNCTION("IFERROR(INDEX(FILTER(Registrations!$E$2:$E100,Registrations!$H$2:$H100=$C90,Registrations!$L$2:$L100<>""Hủy"",Registrations!$L$2:$L100<>""Từ chối""),1),"""")"),"") | I90: =IFERROR(__xludf.DUMMYFUNCTION("IF(F90=0,"""",IF(IFERROR(INDEX(FILTER(Registrations!$F$2:$F100,Registrations!$H$2:$H100=$C90,Registrations!$L$2:$L100<>""Hủy"",Registrations!$L$2:$L100<>""Từ chối""),1),"""")=$A90,""Khớp"",""Sai kho""))"),"") | J90: GoodSet | K90: 9745000
A91: AYC | B91: 90 | C91: #090 | D91: 55UA8450PSA.ATV | E91: =IF(F91=0,"Còn trống",IF(F91=1,"Đã đăng ký","Trùng đăng ký")) -> Còn trống | F91: =COUNTIFS(Registrations!$H$2:$H100,$C91,Registrations!$L$2:$L100,"<>Hủy",Registrations!$L$2:$L100,"<>Từ chối") -> 0 | G91: =IFERROR(__xludf.DUMMYFUNCTION("IFERROR(INDEX(FILTER(Registrations!$D$2:$D100,Registrations!$H$2:$H100=$C91,Registrations!$L$2:$L100<>""Hủy"",Registrations!$L$2:$L100<>""Từ chối""),1),"""")"),"") | H91: =IFERROR(__xludf.DUMMYFUNCTION("IFERROR(INDEX(FILTER(Registrations!$E$2:$E100,Registrations!$H$2:$H100=$C91,Registrations!$L$2:$L100<>""Hủy"",Registrations!$L$2:$L100<>""Từ chối""),1),"""")"),"") | I91: =IFERROR(__xludf.DUMMYFUNCTION("IF(F91=0,"""",IF(IFERROR(INDEX(FILTER(Registrations!$F$2:$F100,Registrations!$H$2:$H100=$C91,Registrations!$L$2:$L100<>""Hủy"",Registrations!$L$2:$L100<>""Từ chối""),1),"""")=$A91,""Khớp"",""Sai kho""))"),"") | J91: GoodSet | K91: 7795000

Sheet Divisions
A1: Bộ Phận | B1: Nhóm
A2: CUSTOMER CARE & SERVICE DIRECTOR | B2: Quản lý & khác
A3: D2C DEPARTMENT HEAD | B3: Quản lý & khác
A4: ES CAC PM | B4: Quản lý & khác
A5: GTM DEPARTMENT | B5: Quản lý & khác
A6: HCM BRANCH | B6: HCM
A7: HCM BUSINESS PLANNING | B7: HCM
A8: HCM DEMAND PLANNING | B8: HCM
A9: HCM DX Marketing | B9: HCM
A10: HCM MARKETING SUPPORT (B2B) | B10: HCM
A11: HCM MOBILE FIELD TEST | B11: HCM
A12: HCM NEW BIZ DEVELOPMENT | B12: HCM
... A174: OTHER | B174: OTHER

Sheet Config
A1: Key | B1: Value | C1: Description
A2: CAMPAIGN_CODE | C2: Mã đợt bán, ví dụ IS-2026-10-01
A3: CAMPAIGN_NAME | C3: Tên đợt bán hiển thị trên trang đăng ký
A4: OPEN_TIME | C4: Thời điểm mở cổng (dd/mm/yyyy hh:mm)
A5: CLOSE_TIME | C5: Hạn chót đăng ký (dd/mm/yyyy hh:mm)
A6: MAX_PER_EMPLOYEE | B6: 1 | C6: Hạn mức sản phẩm cho mỗi nhân viên (theo portal)
A7: WAREHOUSES | B7: AYA, AYB, AYC | C7: Danh sách kho
A8: SLOT_TOTAL | B8: =COUNTA(Slots!$C$2:$C$91) -> 90 | C8: Tự đếm từ sheet Slots
A9: PIC_EMAIL_PRIMARY | C9: Email PM phụ trách, nhận thông báo đăng ký
A10: PIC_EMAIL_CC | C10: Email CC (để trống nếu không có)
A11: PIC_NAME_PRIMARY | C11: Tên hiển thị PM phụ trách
A12: BANK_ACCOUNT_NAME | B12: CÔNG TY TNHH LG ELECTRONICS VIỆT NAM HẢI PHÒNG | C12: Lấy từ bản mẫu portal. Cần Tài chính xác nhận trước khi dùng
A13: BANK_ACCOUNT_NO | B13: 0991000012525 | C13: Lấy từ bản mẫu portal. Cần Tài chính xác nhận trước khi dùng
A14: BANK_NAME | B14: Vietcombank - Chi nhánh Tây Hồ | C14: Lấy từ bản mẫu portal. Cần Tài chính xác nhận trước khi dùng
A15: TRANSFER_SYNTAX | B15: [Mã NV] - [Họ Tên] - [Mã Model] - [Slot ID] | C15: Cú pháp nội dung chuyển khoản
A17: Ô nền vàng: cần điền hoặc cần xác nhận trước khi mở đợt bán.

Sheet ActivityLog
A1: Timestamp | B1: Action | C1: Mã NV | D1: Slot ID | E1: User Agent | F1: Details
A2: 46293.742 | B2: REGISTER | C2: TEST001 | D2: #090 | E2: TEST-Claude | F2: Dòng 2
A3: 46293.742 | B3: REGISTER_REJECTED_DUP_SLOT | C3: TEST002 | D3: #090 | E3: TEST-Claude | F3: Slot đã có người đăng ký, không ghi đơn
A4: 46293.742 | B4: PAYMENT | C4: TEST001 | D4: #090 | E4: TEST-Claude | F4: Dòng 2 | chưa có file biên lai
A5: 46293.88 | B5: REGISTER | C5: TESTC05 | D5: #089 | E5: TEST-dongthoi | F5: Dòng 3
A6: 46293.88 | B6: REGISTER_REJECTED_DUP_SLOT | C6: TESTC03 | D6: #089 | E6: TEST-dongthoi | F6: Slot đã có người đăng ký, không ghi đơn
A7: 46293.88 | B7: REGISTER_REJECTED_DUP_SLOT | C7: TESTC02 | D7: #089 | E7: TEST-dongthoi | F7: Slot đã có người đăng ký, không ghi đơn
A8: 46293.88 | B8: REGISTER_REJECTED_DUP_SLOT | C8: TESTC04 | D8: #089 | E8: TEST-dongthoi | F8: Slot đã có người đăng ký, không ghi đơn
A9: 46293.88 | B9: REGISTER_REJECTED_DUP_SLOT | C9: TESTC01 | D9: #089 | E9: TEST-dongthoi | F9: Slot đã có người đăng ký, không ghi đơn
A10: 46293.888 | B10: REGISTER_REJECTED_DUP_SLOT | C10: TESTL1 | D10: #088 | E10: TEST-v73 | F10: Slot đã có người đăng ký, không ghi đơn
A11: 46293.888 | B11: REGISTER_REJECTED_DUP_SLOT | C11: TESTL4 | D11: #088 | E11: TEST-v73 | F11: Slot đã có người đăng ký, không ghi đơn
A12: 46293.888 | B12: REGISTER | C12: TESTL9 | D12: #088 | E12: TEST-v73 | F12: Dòng 4
A13: 46293.888 | B13: REGISTER_REJECTED_DUP_SLOT | C13: TESTL5 | D13: #088 | E13: TEST-v73 | F13: Slot đã có người đăng ký, không ghi đơn
... A19: 46293.888 | B19: REGISTER_REJECTED_DUP_SLOT | C19: TESTL2 | D19: #088 | E19: TEST-v73 | F19: Slot đã có người đăng ký, không ghi đơn
A20: 46293.888 | B20: LOOKUP_NOT_FOUND | C20: TESTL9 | E20: TEST-v73 | F20: Tra cứu không khớp
A21: 46293.889 | B21: REGISTER_REPEAT | C21: TESTL9 | D21: #088 | E21: TEST-v731 | F21: Gửi lại, đơn đã có ở dòng 4, không ghi thêm
A22: 46293.89 | B22: REGISTER | C22: TESTM19 | D22: #087 | E22: TEST-v731 | F22: Dòng 5
A23: 46293.89 | B23: REGISTER_REJECTED_DUP_SLOT | C23: TESTM17 | D23: #087 | E23: TEST-v731 | F23: Slot đã có người đăng ký, không ghi đơn
A24: 46293.89 | B24: REGISTER_REJECTED_DUP_SLOT | C24: TESTM12 | D24: #087 | E24: TEST-v731 | F24: Slot đã có người đăng ký, không ghi đơn
A25: 46293.89 | B25: REGISTER_REJECTED_DUP_SLOT | C25: TESTM14 | D25: #087 | E25: TEST-v731 | F25: Slot đã có người đăng ký, không ghi đơn
A26: 46293.89 | B26: REGISTER_REJECTED_DUP_SLOT | C26: TESTM9 | D26: #087 | E26: TEST-v731 | F26: Slot đã có người đăng ký, không ghi đơn
A27: 46293.89 | B27: REGISTER_REJECTED_DUP_SLOT | C27: TESTM10 | D27: #087 | E27: TEST-v731 | F27: Slot đã có người đăng ký, không ghi đơn
A28: 46293.89 | B28: REGISTER_REJECTED_DUP_SLOT | C28: TESTM8 | D28: #087 | E28: TEST-v731 | F28: Slot đã có người đăng ký, không ghi đơn
A29: 46293.89 | B29: REGISTER_REJECTED_DUP_SLOT | C29: TESTM3 | D29: #087 | E29: TEST-v731 | F29: Slot đã có người đăng ký, không ghi đơn
A30: 46293.89 | B30: REGISTER_REJECTED_DUP_SLOT | C30: TESTM5 | D30: #087 | E30: TEST-v731 | F30: Slot đã có người đăng ký, không ghi đơn
A31: 46293.89 | B31: REGISTER_REJECTED_DUP_SLOT | C31: TESTM15 | D31: #087 | E31: TEST-v731 | F31: Slot đã có người đăng ký, không ghi đơn
A32: 46293.89 | B32: REGISTER_REJECTED_DUP_SLOT | C32: TESTM16 | D32: #087 | E32: TEST-v731 | F32: Slot đã có người đăng ký, không ghi đơn
... A40: 46294.634 | B40: REGISTER | C40: TESTT1 | D40: #090 | E40: TEST-v74 | F40: Dòng 6

Sheet AutoEmail
A1: Họ Tên | B1: Mã NV | C1: Email | D1: Loại Email | E1: Thời Gian Gửi
